{
  "comment": "This file was autogenerated. Do not modify it by hand, instead use: pnpm update-multichain",
  "chains": [
    {
      "id": "10",
      "name": "Optimism"
    },
    {
      "id": "100",
      "name": "Gnosis"
    },
    {
      "id": "10000",
      "name": "Smart Bitcoin Cash"
    },
    {
      "id": "10001",
      "name": "ETHPoW"
    },
    {
      "id": "1024",
      "name": "CLV Parachain"
    },
    {
      "id": "1030",
      "name": "Conflux eSpace"
    },
    {
      "id": "106",
      "name": "Velas EVM"
    },
    {
      "id": "108",
      "name": "ThunderCore"
    },
    {
      "id": "1088",
      "name": "Metis Andromeda"
    },
    {
      "id": "1111"
    },
    {
      "id": "122",
      "name": "Fuse"
    },
    {
      "id": "1234"
    },
    {
      "id": "128",
      "name": "Huobi ECO Chain"
    },
    {
      "id": "1284",
      "name": "Moonbeam"
    },
    {
      "id": "1285",
      "name": "Moonriver"
    },
    {
      "id": "1294",
      "name": "Boba Network Bobabeam"
    },
    {
      "id": "1313161554"
    },
    {
      "id": "137",
      "name": "Polygon"
    },
    {
      "id": "1666600000",
      "name": "Harmony Shard 0"
    },
    {
      "id": "199",
      "name": "BitTorrent Chain"
    },
    {
      "id": "2000",
      "name": "Dogechain"
    },
    {
      "id": "2001",
      "name": "Milkomeda C1"
    },
    {
      "id": "2002"
    },
    {
      "id": "2025",
      "name": "Rangers Protocol"
    },
    {
      "id": "2109"
    },
    {
      "id": "2222",
      "name": "Kava EVM"
    },
    {
      "id": "24",
      "name": "Dithereum"
    },
    {
      "id": "24734",
      "name": "MintMe.com"
    },
    {
      "id": "25",
      "name": "Cronos Mainnet Beta"
    },
    {
      "id": "250",
      "name": "Fantom"
    },
    {
      "id": "256256",
      "name": "CMP"
    },
    {
      "id": "288",
      "name": "Boba Network"
    },
    {
      "id": "30",
      "name": "RSK"
    },
    {
      "id": "321",
      "name": "KCC"
    },
    {
      "id": "32520"
    },
    {
      "id": "32659",
      "name": "Fusion"
    },
    {
      "id": "336",
      "name": "Shiden"
    },
    {
      "id": "40",
      "name": "Telos EVM"
    },
    {
      "id": "42161",
      "name": "Arbitrum One"
    },
    {
      "id": "42170",
      "name": "Arbitrum Nova"
    },
    {
      "id": "42220",
      "name": "Celo"
    },
    {
      "id": "42262",
      "name": "Oasis Emerald ParaTime"
    },
    {
      "id": "43114",
      "name": "Avalanche C-Chain"
    },
    {
      "id": "4689",
      "name": "IoTeX Network"
    },
    {
      "id": "47805",
      "name": "REI"
    },
    {
      "id": "5",
      "name": "Goerli"
    },
    {
      "id": "56",
      "name": "Binance Smart Chain"
    },
    {
      "id": "57",
      "name": "Syscoin"
    },
    {
      "id": "58",
      "name": "Ontology"
    },
    {
      "id": "592",
      "name": "Astar"
    },
    {
      "id": "61",
      "name": "Ethereum Classic"
    },
    {
      "id": "66",
      "name": "OKXChain"
    },
    {
      "id": "71402",
      "name": "Godwoken"
    },
    {
      "id": "8217",
      "name": "Klaytn Mainnet Cypress"
    },
    {
      "id": "86",
      "name": "GateChain"
    },
    {
      "id": "88",
      "name": "TomoChain"
    },
    {
      "id": "9001",
      "name": "Evmos"
    },
    {
      "id": "ADA"
    },
    {
      "id": "APT"
    },
    {
      "id": "NEAR",
      "name": "Near"
    },
    {
      "id": "SOL"
    },
    {
      "id": "XRP",
      "name": "XRP"
    }
  ],
  "escrows": [
    {
      "type": "any",
      "address": "0x015Cea338Ce68bd912B3c704620C6000eE9F4Ab9",
      "tokens": ["0x5f944B0c4315Cb7c3a846b025AB4045da44abf6c"]
    },
    {
      "type": "any",
      "address": "0x02a2b736F9150d36C0919F3aCEE8BA2A92FBBb40",
      "tokens": ["0xA849EaaE994fb86Afa73382e9Bd88c2B6b18Dc71"]
    },
    {
      "type": "any",
      "address": "0x03A9bdbA596c93797f45e9D90CF1e3A3d8191EF0",
      "tokens": ["0x136210A5c79d2435432e443f7155D9d83600ac70"]
    },
    {
      "type": "any",
      "address": "0x05F2972cd67705E7f2DcBfFD0Daa3F939B61020B",
      "tokens": ["0x7a5d3A9Dcd33cb8D527f7b5F96EB4Fef43d55636"]
    },
    {
      "type": "any",
      "address": "0x0615Dbba33Fe61a31c7eD131BDA6655Ed76748B1",
      "tokens": ["0xC02aaA39b223FE8D0A0e5C4F27eAD9083C756Cc2"]
    },
    {
      "type": "any",
      "address": "0x063069F9bEAB2B01153C87622f6Ed8f693ed5215",
      "tokens": ["0x1b308d8c92EE6b06faBAFE3c8ed21a9DbBE5FaCD"]
    },
    {
      "type": "any",
      "address": "0x06E2DDd17F1043c0a4Cbe72cc7c256E4d8a3E374",
      "tokens": ["0xd1ba9BAC957322D6e8c07a160a3A8dA11A0d2867"]
    },
    {
      "type": "any",
      "address": "0x0802d66f029c46E042b74d543fC43B6705ccb4ba",
      "tokens": ["0x5c2fCe5a43A56FC158a5a86CAc4FCC4fBDc577F4"]
    },
    {
      "type": "any",
      "address": "0x08111ECEe4eB8D766aBDF6dCBFCa81949c0B0891",
      "tokens": ["0x035dF12E0F3ac6671126525f1015E47D79dFEDDF"]
    },
    {
      "type": "any",
      "address": "0x0914D4CCc4154cA864637B0B653Bc5Fd5e1d3ecF",
      "tokens": ["0x5A98FcBEA516Cf06857215779Fd812CA3beF1B32"]
    },
    {
      "type": "any",
      "address": "0x09211Dc67f9fe98Fb7bBB91Be0ef05f4a12FA2b2",
      "tokens": ["0xAcfa209Fb73bF3Dd5bBfb1101B9Bc999C49062a5"]
    },
    {
      "type": "any",
      "address": "0x09b809fbB0a1fA04916Fb47b24DBc33529FD0C73",
      "tokens": ["0x01FB70eA8AcFDd5435c8e8bd1531d96D57cEd0ec"]
    },
    {
      "type": "any",
      "address": "0x0aC06321050Defb485340c3509A5405F9d7655c7",
      "tokens": ["0x4691937a7508860F876c9c0a2a617E7d9E945D4B"]
    },
    {
      "type": "any",
      "address": "0x0B23341fA1Da0171f52aA8Ef85f3946b44d35ac0",
      "tokens": ["0xb546c4a4FbFb0Ae97b589e6887d198d11e9f375e"]
    },
    {
      "type": "any",
      "address": "0x0bd19f6447cd676255C7C7B00428462B3dA67e3a",
      "tokens": ["0x0000000000085d4780B73119b644AE5ecd22b376"]
    },
    {
      "type": "any",
      "address": "0x0c5F149362cA17Eac5D18E6912Ab4F5aEabf88E6",
      "tokens": ["0xc7fF1e126cC81e816915FF48c940ED9d4E6d05d6"]
    },
    {
      "type": "any",
      "address": "0x0C8AF3016eec474F79373BE89F534073bB33Fe4d",
      "tokens": ["0x8Dbd43048e60e3c9a602de7F5f1F1c8A9C6Ffee1"]
    },
    {
      "type": "any",
      "address": "0x0E1b539Eaf71d5D025f8ce90cA2256b4Cf3e94B1",
      "tokens": ["0xD533a949740bb3306d119CC777fa900bA034cd52"]
    },
    {
      "type": "any",
      "address": "0x0F65f65792d4B286b6f2Ff373eE1c1631f71C635",
      "tokens": ["0x92a42Db88Ed0F02c71D439e55962Ca7CAB0168b5"]
    },
    {
      "type": "any",
      "address": "0x0f7Efb2e96B9681950f96D3D18ce0BF68d60fD7e",
      "tokens": ["0x808507121B80c02388fAd14726482e061B8da827"]
    },
    {
      "type": "basic",
      "address": "0x10c6b61DbF44a083Aec3780aCF769C77BE747E23",
      "tokens": [
        "0x0bc529c00C6401aEF6D220BE8C6Ea1667F6Ad93e",
        "0x147faF8De9d8D8DAAE129B187F0D02D819126750",
        "0x1f9840a85d5aF5bf1D1762F925BDADdC4201F984",
        "0x2260FAC5E5542a773Aa44fBCfeDf7C193bc2C599",
        "0x32a7C02e79c4ea1008dD6564b35F131428673c41",
        "0x3432B6A60D23Ca0dFCa7761B7ab56459D9C964D0",
        "0x514910771AF9Ca656af840dff83E8264EcF986CA",
        "0x59E9261255644c411AfDd00bD89162d09D862e38",
        "0x6B175474E89094C44Da98b954EedeAC495271d0F",
        "0x6B3595068778DD592e39A122f4f5a5cF09C90fE2",
        "0x6B4c7A5e3f0B99FCD83e9c089BDDD6c7FCe5c611",
        "0x7Fc66500c84A76Ad7e9c93437bFc5Ac33E2DDaE9",
        "0x853d955aCEf822Db058eb8505911ED77F175b99e",
        "0x91dFbEE3965baAEE32784c2d546B7a0C62F268c9",
        "0x967da4048cD07aB37855c090aAF366e4ce1b9F48",
        "0xA0b86991c6218b36c1d19D4a2e9Eb0cE3606eB48",
        "0xAF691508BA57d416f895e32a1616dA1024e882D2",
        "0xBc17729fDf562723f0267F79FF25aDE441056d87",
        "0xC011a73ee8576Fb46F5E1c5751cA3B9Fe0af2a6F",
        "0xD533a949740bb3306d119CC777fa900bA034cd52",
        "0xbcD4b7dE6fde81025f74426D43165a5b0D790Fdd",
        "0xbd1848e1491d4308Ad18287A745DD4DB2A4BD55B",
        "0xc3D088842DcF02C13699F936BB83DFBBc6f721Ab",
        "0xdAC17F958D2ee523a2206206994597C13D831ec7",
        "ETH"
      ]
    },
    {
      "type": "any",
      "address": "0x11eb3aA66FE1f2B75cB353D3e874E96968182BdA",
      "tokens": ["0x9f8F72aA9304c8B593d555F12eF6589cC3A579A2"]
    },
    {
      "type": "basic",
      "address": "0x13B432914A996b0A48695dF9B2d701edA45FF264",
      "tokens": [
        "0x0bc529c00C6401aEF6D220BE8C6Ea1667F6Ad93e",
        "0x1f9840a85d5aF5bf1D1762F925BDADdC4201F984",
        "0x2e1E15C44Ffe4Df6a0cb7371CD00d5028e571d14",
        "0x514910771AF9Ca656af840dff83E8264EcF986CA",
        "0x6B175474E89094C44Da98b954EedeAC495271d0F",
        "0x80CD73baDb406eA36B9a7CDeb8df06AeFa7E12d9",
        "0xc00e94Cb662C3520282E6f5717214004A7f26888",
        "0xd26114cd6EE289AccF82350c8d8487fedB8A0C07",
        "0xd47bDF574B4F76210ed503e0EFe81B58Aa061F3d",
        "0xdAC17F958D2ee523a2206206994597C13D831ec7",
        "0xe53EC727dbDEB9E2d5456c3be40cFF031AB40A55",
        "ETH"
      ]
    },
    {
      "type": "any",
      "address": "0x14D3E0FfbD62c9618C73ebB6F9c1CBCD23B6AbE1",
      "tokens": ["0xc36b4311B21Fc0c2eAd46f1eA6ce97c9C4D98D3d"]
    },
    {
      "type": "any",
      "address": "0x152c0f9c32C393961e9803a9467B2194E1c00b21",
      "tokens": ["0x231CC03E6d8b7368eC2aBfAfb5f73D216c8af980"]
    },
    {
      "type": "any",
      "address": "0x15a3FE3e6B8a5C01b1BfE72C76660C897368Eec0",
      "tokens": ["0x8C543AED163909142695f2d2aCd0D55791a9Edb9"]
    },
    {
      "type": "any",
      "address": "0x1608278E54FB9E070cb109234d111Ff3A359612b",
      "tokens": ["0xD38B1159c8aEE064Af2D869Afa1c2c1632da8B97"]
    },
    {
      "type": "any",
      "address": "0x16A66F530D0a755d10Fd7C232B6b170d8617B168",
      "tokens": ["0x7f78A88d77FA03F3cE4a94b14A0e1abB5eEEEDD7"]
    },
    {
      "type": "any",
      "address": "0x16abA2d28329620F31D44748EC82FA08daA50B86",
      "tokens": ["0x12BB890508c125661E03b09EC06E404bc9289040"]
    },
    {
      "type": "any",
      "address": "0x1748E1A07E82762660b4e57838B570dCb73bF75D",
      "tokens": ["0xB2979Ab4705FA0621FCaB059748B4e77dd76b78e"]
    },
    {
      "type": "basic",
      "address": "0x183D0dC5867c01bFB1dbBc41d6a9d3dE6e044626",
      "tokens": [
        "0x3432B6A60D23Ca0dFCa7761B7ab56459D9C964D0",
        "0x7aE1D57b58fA6411F32948314BadD83583eE0e8C",
        "0x853d955aCEf822Db058eb8505911ED77F175b99e",
        "0xD91E9a0fEf7C0fa4EBdAF4d0aCF55888949A2a9b",
        "0xaa61D5dec73971CD4a026ef2820bB87b4a4Ed8d6",
        "0xb26C4B3Ca601136Daf98593feAeff9E0CA702a8D",
        "0xdBdb4d16EdA451D0503b854CF79D55697F90c8DF",
        "0xf16e81dce15B08F326220742020379B855B87DF9",
        "ETH"
      ]
    },
    {
      "type": "any",
      "address": "0x19193F450086d0442157b852081976D41657aD56",
      "tokens": ["0x4C4D878faE704ffF9E00325f7C2bC758489202EC"]
    },
    {
      "type": "any",
      "address": "0x19F36BbB75cFb2969486d46a95E37c74A90C7CBb",
      "tokens": ["0x8EEdEFe828A0f16C8fc80e46a87Bc0f1De2d960c"]
    },
    {
      "type": "any",
      "address": "0x1B4EaD1f89Eebef694eFa6F9B95D61A429C05BDB",
      "tokens": ["0x8642A849D0dcb7a15a974794668ADcfbe4794B56"]
    },
    {
      "type": "any",
      "address": "0x1c2E7118591ec1b6122e4fE3d645706a9747b10E",
      "tokens": ["0x1b40183EFB4Dd766f11bDa7A7c3AD8982e998421"]
    },
    {
      "type": "any",
      "address": "0x1Cb1284CF62C3E593a8f49EEf3db37AD20467Bed",
      "tokens": ["0x7D1AfA7B718fb893dB30A3aBc0Cfc608AaCfeBB0"]
    },
    {
      "type": "any",
      "address": "0x1e1085eFaA63EDFE74aaD7C05a28EAE4ef917C3F",
      "tokens": ["0x0E95B13539D0381AB20B4E2893E926Fc99b3d8Dc"]
    },
    {
      "type": "any",
      "address": "0x1FbBc7dBa1eF75ff43F955a5B9CeeC3Cc1692Cd8",
      "tokens": ["0xB4d930279552397bbA2ee473229f89Ec245bc365"]
    },
    {
      "type": "any",
      "address": "0x1fF9b7Dc66BB8CC7819E875B6739409B3A42111b",
      "tokens": ["0x7659CE147D0e714454073a5dd7003544234b6Aa0"]
    },
    {
      "type": "any",
      "address": "0x20CF1b6E9d856321ed4686877CF4538F2C84B4dE",
      "tokens": ["0x71dc40668682a124231301414167E4CF7f55383C"]
    },
    {
      "type": "any",
      "address": "0x2127b96A05f9bF9095913d1e8b7bdB203a683A9f",
      "tokens": ["0xAfAEb84415c1cd2bC99cd1F5F0B3090baE1BEb6c"]
    },
    {
      "type": "any",
      "address": "0x21804205C744dd98fbc87898704564d5094bB167",
      "tokens": ["0xF1bB87563A122211d40d393eBf1c633c330377F9"]
    },
    {
      "type": "any",
      "address": "0x22648C12acD87912EA1710357B1302c6a4154Ebc",
      "tokens": ["0xdAC17F958D2ee523a2206206994597C13D831ec7"]
    },
    {
      "type": "any",
      "address": "0x252D978ecBfeA2009e1a842776Dab8035a9C38a8",
      "tokens": ["0xCC4304A31d09258b0029eA7FE63d032f52e44EFe"]
    },
    {
      "type": "any",
      "address": "0x25A528af62e56512A19ce8c3cAB427807c28CC19",
      "tokens": ["0x3b1388eB39c72D2145f092C01067C02Bb627d4BE"]
    },
    {
      "type": "any",
      "address": "0x26EAF31489662587232990Fc6981026D4175CD40",
      "tokens": ["0x783C68814126b66B9242C4c6538Ae47dB5e33169"]
    },
    {
      "type": "any",
      "address": "0x27BeF51F483A3D41E7A816Dae22B47E249dB5650",
      "tokens": ["0x7Cfea0DD176651E7B5a1CeD9c4fAf8Ee295315FD"]
    },
    {
      "type": "any",
      "address": "0x2AC03BF434db503f6f5F85C3954773731Fc3F056",
      "tokens": ["0xC02aaA39b223FE8D0A0e5C4F27eAD9083C756Cc2"]
    },
    {
      "type": "any",
      "address": "0x2aD402655243203fcfa7dCB62F8A08cc2BA88ae0",
      "tokens": ["0x6781a0F84c7E9e846DCb84A9a5bd49333067b104"]
    },
    {
      "type": "any",
      "address": "0x2cF7d99C1bff7Caa25B737C909637948e6E7781E",
      "tokens": ["0xb31eF9e52d94D4120eb44Fe1ddfDe5B4654A6515"]
    },
    {
      "type": "any",
      "address": "0x2d72A97a31Dc920dB03330780d30074626e39C8A",
      "tokens": ["0x1CCAA0F2a7210d76E1fDec740d5F323E2E1b1672"]
    },
    {
      "type": "any",
      "address": "0x2eAa12c0c76ea8192d82B63F8dbBb7EC2a270295",
      "tokens": ["0xA803778AB953d3FfE4FBD20Cfa0042eCeFE8319D"]
    },
    {
      "type": "any",
      "address": "0x2eF4A574b72E1f555185AfA8A09c6d1A8AC4025C",
      "tokens": ["0xA130E3a33a4d84b04c3918c4E5762223Ae252F80"]
    },
    {
      "type": "basic",
      "address": "0x2F10c5eE93ac666dA72195abA8a49FD6D27fA02F",
      "tokens": [
        "0x2260FAC5E5542a773Aa44fBCfeDf7C193bc2C599",
        "0x9Ed8e7C9604790F7Ec589F99b94361d8AAB64E5E"
      ]
    },
    {
      "type": "any",
      "address": "0x301DE15579C37d1e1cC8B46D74324b885A77291B",
      "tokens": ["0x7815bDa662050D84718B988735218CFfd32f75ea"]
    },
    {
      "type": "any",
      "address": "0x31dF3cfc1113b0AFA2120887DB216948c36Eb77C",
      "tokens": ["0x53884b61963351C283118a8E1Fc05BA464a11959"]
    },
    {
      "type": "any",
      "address": "0x34290390c2fdEdB968E7128Af26A98E731B781D0",
      "tokens": ["0xe2Fc859C838F31C1450448f4FeD92e3284aE49E9"]
    },
    {
      "type": "any",
      "address": "0x34324E1598Bf02cCD3deA93f4E332b5507097473",
      "tokens": ["0xfd30C9BEA1A952FEeEd2eF2C6B2Ff8A8FC4aAD07"]
    },
    {
      "type": "any",
      "address": "0x34f380a4e3389e99C0369264453523Bbe5aF7faB",
      "tokens": ["0xDfDd3459D4F87234751696840092ee20C970Fb07"]
    },
    {
      "type": "basic",
      "address": "0x353B98DDc927173005dD8B293B043Bd950cDA468",
      "tokens": [
        "0x2260FAC5E5542a773Aa44fBCfeDf7C193bc2C599",
        "0x6B175474E89094C44Da98b954EedeAC495271d0F",
        "0xA0b86991c6218b36c1d19D4a2e9Eb0cE3606eB48",
        "ETH"
      ]
    },
    {
      "type": "basic",
      "address": "0x3696f44F2B7FE51486f81D2639Ff895202614711",
      "tokens": ["0xD533a949740bb3306d119CC777fa900bA034cd52"]
    },
    {
      "type": "basic",
      "address": "0x373590a576ccb8143f377DB5f1c16F9f8528a8B4",
      "tokens": [
        "0x2260FAC5E5542a773Aa44fBCfeDf7C193bc2C599",
        "0x5a9C8c6406d341A16aa3010108026f45fc372168",
        "0x6B175474E89094C44Da98b954EedeAC495271d0F",
        "0xA0b86991c6218b36c1d19D4a2e9Eb0cE3606eB48",
        "0xdAC17F958D2ee523a2206206994597C13D831ec7",
        "ETH"
      ]
    },
    {
      "type": "any",
      "address": "0x37C24675E4a0DFCE683c51e1746599F1E2517Eb5",
      "tokens": ["0xAaAAAA20D9E0e2461697782ef11675f668207961"]
    },
    {
      "type": "any",
      "address": "0x38389eB214C4AC1CDDa7A7582Ab01e8a9bB548bA",
      "tokens": ["0x2cc71c048A804Da930e28E93F3211dC03c702995"]
    },
    {
      "type": "any",
      "address": "0x3915C77Dc839d97e875613a5b64179aCC1Da97Df",
      "tokens": ["0xAC51066d7bEC65Dc4589368da368b212745d63E8"]
    },
    {
      "type": "any",
      "address": "0x3b9e3b5c616A1A038fDc190758Bbe9BAB6C7A857",
      "tokens": ["0xE0aD1806Fd3E7edF6FF52Fdb822432e847411033"]
    },
    {
      "type": "any",
      "address": "0x3BD2dFd03BC7c3011ed7fb8c4d0949B382726cee",
      "tokens": ["0x88A9A52F944315D5B4e917b9689e65445C401E83"]
    },
    {
      "type": "any",
      "address": "0x3bd9856BF578910b55261d45d9148d61C177B092",
      "tokens": ["0x5f4c148D17Effd165C2e2d46b46d2BD6e3eBDC3e"]
    },
    {
      "type": "any",
      "address": "0x3D632d9e1a60a0880Dd45E61f279D919b5748377",
      "tokens": ["0xAE12C5930881c53715B369ceC7606B70d8EB229f"]
    },
    {
      "type": "any",
      "address": "0x3E01B7E242D5AF8064cB9A8F9468aC0f8683617c",
      "tokens": ["0x7fC3eC3574d408F3b59CD88709baCb42575EBF2b"]
    },
    {
      "type": "any",
      "address": "0x3fF1Af9E583d3790ec51E1407c9E94D8D1133dC3",
      "tokens": ["0xb753428af26E81097e7fD17f40c88aaA3E04902c"]
    },
    {
      "type": "any",
      "address": "0x403BEB734e0C7E87D632a4EA1B290059E3B3A3c9",
      "tokens": ["0x03ab458634910AaD20eF5f1C8ee96F1D6ac54919"]
    },
    {
      "type": "any",
      "address": "0x40D4c6CecA870A0439dC0232D40cF8be8B425bAf",
      "tokens": ["0x28b5E12CcE51f15594B0b91d5b5AdaA70F684a02"]
    },
    {
      "type": "any",
      "address": "0x40DF1Ae6074C35047BFF66675488Aa2f9f6384F3",
      "tokens": ["0x0B6F3c17e1626a7cBfA4302CE4E3c45522d23A83"]
    },
    {
      "type": "any",
      "address": "0x410A7bf502414B2f0cAAd204de5782077AC6478F",
      "tokens": ["0x84cA8bc7997272c7CfB4D0Cd3D55cd942B3c9419"]
    },
    {
      "type": "any",
      "address": "0x413fbFDCE9B5AfB65B6147FBBc970148b79e706A",
      "tokens": ["0x16ba8Efe847EBDFef99d399902ec29397D403C30"]
    },
    {
      "type": "any",
      "address": "0x41471fbf66dafB95b682AfAF1426bEe11F25e10a",
      "tokens": ["0x18a1Ea69A50A85752b7bC204a2c45A95Ce6E429d"]
    },
    {
      "type": "any",
      "address": "0x4187252a32a32E4d44C1BD15BDA675dc92e42dF5",
      "tokens": ["0x7CBCFd88C952a1f5EAa954945EBC7ED8f1015ec0"]
    },
    {
      "type": "any",
      "address": "0x419fa2e21092D834e3b02bD0802DEE329c84268A",
      "tokens": ["0x4eE438be38F8682ABB089F2BFeA48851C5E71EAF"]
    },
    {
      "type": "any",
      "address": "0x4492FA5E20899778259f852D2a3FF76E6D074621",
      "tokens": ["0x68257309fCdfE1e6eDb592DA97aC8215fe583908"]
    },
    {
      "type": "basic",
      "address": "0x46290B0c3A234E3d538050d8F34421797532A827",
      "tokens": [
        "0x0bc529c00C6401aEF6D220BE8C6Ea1667F6Ad93e",
        "0x16EA01aCB4b0Bca2000ee5473348B6937ee6f72F",
        "0x1f9840a85d5aF5bf1D1762F925BDADdC4201F984",
        "0x514910771AF9Ca656af840dff83E8264EcF986CA",
        "0x584bC13c7D411c00c01A62e8019472dE68768430",
        "0x6B175474E89094C44Da98b954EedeAC495271d0F",
        "0xA8e7AD77C60eE6f30BaC54E2E7c0617Bd7B5A03E",
        "0xCb4e8CafEDa995da5cEdfda5205BD5664a12b848",
        "0xc00e94Cb662C3520282E6f5717214004A7f26888",
        "0xd26114cd6EE289AccF82350c8d8487fedB8A0C07",
        "0xdAC17F958D2ee523a2206206994597C13D831ec7",
        "0xf21661D0D1d76d3ECb8e1B9F1c923DBfffAe4097",
        "ETH"
      ]
    },
    {
      "type": "any",
      "address": "0x47536F17F4fF30e64A96a7555826b8f9e66ec468",
      "tokens": ["0xD8C1232FcD219286E341271385bd70601503B3D7"]
    },
    {
      "type": "any",
      "address": "0x47736CCbaB8117D09540E4e56Db4089A328ff7a1",
      "tokens": ["0xfB7B4564402E5500dB5bB6d63Ae671302777C75a"]
    },
    {
      "type": "any",
      "address": "0x48844dDBa89799DC40eC31728dAC629802D407f3",
      "tokens": ["0x874464211649Eb0c504903195902415fb6986AaD"]
    },
    {
      "type": "any",
      "address": "0x495b56e08e20C0B6924cD4cadc9Bf4146a64bb52",
      "tokens": ["0x513C3200F227ebB62e3B3d00B7a83779643a71CF"]
    },
    {
      "type": "any",
      "address": "0x496CD9b62B192e04811f38D97b88733f969AfD5d",
      "tokens": ["0xA87135285Ae208e22068AcDBFf64B11Ec73EAa5A"]
    },
    {
      "type": "any",
      "address": "0x49a0400587A7F65072c87c4910449fDcC5c47242",
      "tokens": ["0x44709a920fCcF795fbC57BAA433cc3dd53C44DbE"]
    },
    {
      "type": "any",
      "address": "0x4a0A3902e091cdb3AEc4279a6BFAC50297F0A79e",
      "tokens": ["0xF629cBd94d3791C9250152BD8dfBDF380E2a3B9c"]
    },
    {
      "type": "any",
      "address": "0x4A24b7269459017C999ABABA32962b3CDb436250",
      "tokens": ["0x865377367054516e17014CcdED1e7d814EDC9ce4"]
    },
    {
      "type": "any",
      "address": "0x4b27Cd6E6a5E83d236eAD376D256Fe2F9e9f0d2E",
      "tokens": ["0x6399C842dD2bE3dE30BF99Bc7D1bBF6Fa3650E70"]
    },
    {
      "type": "any",
      "address": "0x4B641f607570B9053035780615f5b56a91F38F90",
      "tokens": ["0x8D6CeBD76f18E1558D4DB88138e2DeFB3909fAD6"]
    },
    {
      "type": "any",
      "address": "0x4D67A556f6FB7d84A857f363518501c831e1348B",
      "tokens": ["0xDE1E704dae0B4051e80DAbB26ab6ad6c12262DA0"]
    },
    {
      "type": "any",
      "address": "0x4e1581f01046eFDd7a1a2CDB0F82cdd7F71F2E59",
      "tokens": ["0x6468e79A80C0eaB0F9A2B574c8d5bC374Af59414"]
    },
    {
      "type": "basic",
      "address": "0x4E67df0f232C3bc985F8a63326D80ce3d9A40400",
      "tokens": [
        "0x2260FAC5E5542a773Aa44fBCfeDf7C193bc2C599",
        "0x2370f9d504c7a6E775bf6E14B3F12846b594cD53",
        "0x286C0936c7Eaf6651099Ab5DAb9ee5A6cB5d229D",
        "0x514910771AF9Ca656af840dff83E8264EcF986CA",
        "0x6B175474E89094C44Da98b954EedeAC495271d0F",
        "0xA0b86991c6218b36c1d19D4a2e9Eb0cE3606eB48",
        "0xa5e48a6E56e164907263e901B98D9b11CCB46C47",
        "0xbd1848e1491d4308Ad18287A745DD4DB2A4BD55B",
        "0xdAC17F958D2ee523a2206206994597C13D831ec7",
        "ETH"
      ]
    },
    {
      "type": "any",
      "address": "0x4e840AADD28DA189B9906674B4Afcb77C128d9ea",
      "tokens": ["0x090185f2135308BaD17527004364eBcC2D37e5F6"]
    },
    {
      "type": "any",
      "address": "0x4f60a160D8C2DDdaAfe16FCC57566dB84D674BD6",
      "tokens": ["0x853d955aCEf822Db058eb8505911ED77F175b99e"]
    },
    {
      "type": "any",
      "address": "0x527c571300bE23e6F157290dEDf9Ac22F7435801",
      "tokens": ["0x397E10ee5e315F69b23cB6c8A913A589b5850c80"]
    },
    {
      "type": "any",
      "address": "0x52DC835D5a36FdF9E6a84603cfEF82298645635C",
      "tokens": ["0x794Baab6b878467F93EF17e2f2851ce04E3E34C8"]
    },
    {
      "type": "basic",
      "address": "0x533e3c0e6b48010873B947bddC4721b1bDFF9648",
      "tokens": [
        "0x012E0e6342308b247F36Ee500ECb14dc77a7a8C1",
        "0x0239d3a3485Ec54511beE9d77D92695E443bf060",
        "0x02F2D4a04E6E01aCE88bD2Cd632875543b2eF577",
        "0x049e119413aB1f1b0fd836e657e3e4BA3ad9CaB8",
        "0x04E0Af0af1b7f0023c6B12af5a94Df59B0e8cF59",
        "0x054D64b73d3D8A21Af3D764eFd76bCaA774f3Bb2",
        "0x056354F3Ff20743aa4c0DA365603871c7000b081",
        "0x0563DCe613D559a47877fFD1593549fb9d3510D6",
        "0x05D3606d5c81EB9b7B18530995eC9B29da05FaBa",
        "0x06677Dc4fE12d3ba3C7CCfD0dF8Cd45e4D4095bF",
        "0x06e0feB0D74106c7adA8497754074D222Ec6BCDf",
        "0x0763fdCCF1aE541A5961815C0872A8c5Bc6DE4d7",
        "0x08ba718F288c3b12B01146816bef9FA03cC635bc",
        "0x09970aec766b6f3223aCA9111555E99DC50Ff13a",
        "0x0Ae055097C6d159879521C384F1D2123D1f195e6",
        "0x0DB8D8b76BC361bAcbB72E2C491E06085A97Ab31",
        "0x0E8d6b471e332F140e7d9dbB99E5E3822F728DA6",
        "0x0E95B13539D0381AB20B4E2893E926Fc99b3d8Dc",
        "0x0c7D5ae016f806603CB1782bEa29AC69471CAb9c",
        "0x0f51bb10119727a7e5eA3538074fb341F56B09Ad",
        "0x0fF6ffcFDa92c53F615a4A75D982f399C989366b",
        "0x106538CC16F938776c7c180186975BCA23875287",
        "0x114B3381b47650c6bEa8A4dcA8d8fa6AFb329678",
        "0x123aB66587361bEbD0141f1Dde69D8075f073450",
        "0x126c121f99e1E211dF2e5f8De2d96Fa36647c855",
        "0x1337DEF16F9B486fAEd0293eb623Dc8395dFE46a",
        "0x1494CA1F11D487c2bBe4543E90080AeBa4BA3C2b",
        "0x16980b3B4a3f9D89E33311B5aa8f80303E5ca4F8",
        "0x1712Aad2C773ee04bdC9114b32163c058321CD85",
        "0x1735Db6AB5BAa19eA55d0AdcEeD7bcDc008B3136",
        "0x177BA0cac51bFC7eA24BAd39d81dcEFd59d74fAa",
        "0x19D97D8fA813EE2f51aD4B4e04EA08bAf4DFfC28",
        "0x1A3496C18d558bd9C6C8f609E1B129f67AB08163",
        "0x1BE66C15731788BaE659B4bdD40d4AA9B3bbca94",
        "0x1BeEF31946fbbb40B877a72E4ae04a8D1A5Cee06",
        "0x1C9922314ED1415c95b9FD453c3818fd41867d0B",
        "0x1F4cb968b76931C494Ff92ED80CCB169ad641cb1",
        "0x1FbD3dF007eB8A7477A1Eab2c63483dCc24EfFD6",
        "0x1b40183EFB4Dd766f11bDa7A7c3AD8982e998421",
        "0x1c23f0F3E06FA0e07C5e661353612A2d63323BC6",
        "0x1d37986F252d0e349522EA6C3B98Cb935495E63E",
        "0x1f19f83fC9a25F3C861260143E36c17706257986",
        "0x20a8CEC5fffea65Be7122BCaB2FFe32ED4Ebf03a",
        "0x20c36f062a31865bED8a5B1e512D9a1A20AA333A",
        "0x21381e026Ad6d8266244f2A583b35F9E4413FA2a",
        "0x217ddEad61a42369A266F1Fb754EB5d3EBadc88a",
        "0x21d486F6B7EB7B556978c5A0C96c79A08Eb841De",
        "0x21fb4DD8C500BE1A9BA27F827217E477217D6225",
        "0x226f7b842E0F0120b7E194D05432b3fd14773a9D",
        "0x22B6C31c2bEB8f2d0d5373146Eed41Ab9eDe3caf",
        "0x232FB065D9d24c34708eeDbF03724f2e95ABE768",
        "0x24E89bDf2f65326b94E36978A7EDeAc63623DAFA",
        "0x24EC2Ca132abf8F6f8a6E24A1B97943e31f256a7",
        "0x256F2d67e52fE834726D2DDCD8413654F5Eb8b53",
        "0x2610F0bFC21EF389fe4D03CFB7De9ac1E6C99D6E",
        "0x26DB5439F651CAF491A87d48799dA81F191bDB6b",
        "0x270371C58D9D775ED73971Dd414656107384f235",
        "0x27054b13b1B798B345b591a4d22e6562d47eA75a",
        "0x2791BfD60D232150Bff86b39B7146c0eaAA2BA81",
        "0x27C4af9A860c4caDc358005F8b48140b2E434A7B",
        "0x28cb7e841ee97947a86B06fA4090C8451f64c0be",
        "0x28fDA76721a8077A5dE802Ab0212849B8c38429E",
        "0x2A039B1D9bBDccBb91be28691b730ca893e5e743",
        "0x2B89bF8ba858cd2FCee1faDa378D5cd6936968Be",
        "0x2C2f7e7C5604D162d75641256b80F1Bf6f4dC796",
        "0x2C9023bBc572ff8dc1228c7858A280046Ea8C9E5",
        "0x2D80f5F5328FdcB6ECeb7Cacf5DD8AEDaEC94e20",
        "0x2aECCB42482cc64E087b6D2e5Da39f5A7A7001f8",
        "0x2baac9330Cf9aC479D819195794d79AD0c7616e3",
        "0x2f1bd435E2b928C1744202daE9400D10A2D569dC",
        "0x30f271C9E86D2B7d00a6376Cd96A1cFBD5F0b9b3",
        "0x31429d1856aD1377A8A0079410B297e1a9e214c2",
        "0x31c2415c946928e9FD1Af83cdFA38d3eDBD4326f",
        "0x31ea0de8119307aA264Bb4b38727aAb4E36b074f",
        "0x327673aE6B33Bd3d90f0096870059994f30Dc8AF",
        "0x32E6C34Cd57087aBBD59B5A4AECC4cB495924356",
        "0x3301Ee63Fb29F863f2333Bd4466acb46CD8323E6",
        "0x33D0568941C0C64ff7e0FB4fbA0B11BD37deEd9f",
        "0x3432B6A60D23Ca0dFCa7761B7ab56459D9C964D0",
        "0x3449FC1Cd036255BA1EB19d65fF4BA2b8903A69a",
        "0x3472A5A71965499acd81997a54BBA8D852C6E53d",
        "0x34f797e7190C131cF630524655A618b5BD8738e7",
        "0x35747eb4C027EbBf0a7f4e642627afCd7Fd8CD7A",
        "0x362bc847A3a9637d3af6624EeC853618a43ed7D2",
        "0x36E43065e977bC72CB86Dbd8405fae7057CDC7fD",
        "0x374CB8C27130E2c9E04F44303f3c8351B9De61C1",
        "0x377d552914E7A104bC22B4F3B6268dDC69615Be7",
        "0x389999216860AB8E0175387A0c90E5c52522C945",
        "0x3A82D3111aB5faF39d847D46023d9090261A658F",
        "0x3A8cCCB969a61532d1E6005e2CE12C200caeCe87",
        "0x3aFfCCa64c2A6f4e3B6Bd9c64CD2C969EFd1ECBe",
        "0x3e780920601D61cEdb860fe9c4a90c9EA6A35E78",
        "0x3fa400483487A489EC9b1dB29C4129063EEC4654",
        "0x4123a133ae3c521FD134D7b13A2dEC35b56c2463",
        "0x4157AA94c04799d8EA1Ca09e8440e6EebBE04830",
        "0x419c4dB4B9e25d6Db2AD9691ccb832C8D9fDA05E",
        "0x41D5D79431A913C4aE7d69a668ecdfE5fF9DFB68",
        "0x436dA116249044E8B4464F0Cf21Dd93311d88190",
        "0x44e2deC86B9F0e0266E9AA66e10323A2bd69CF9A",
        "0x44f262622248027f8E2a8Fb1090c4Cf85072392C",
        "0x46e98FFE40E408bA6412bEb670507e083C8B95ff",
        "0x4740735AA98Dc8aa232BD049f8F0210458E7fCa3",
        "0x48592de8CdED16f6Bb56c896Fe1Affc37630889C",
        "0x48C276e8d03813224bb1e55F953adB6d02FD3E02",
        "0x491E136FF7FF03E6aB097E54734697Bb5802FC1C",
        "0x4C25Bdf026Ea05F32713F00f73Ca55857Fbf6342",
        "0x4C2e59D098DF7b6cBaE0848d66DE2f8A4889b9C3",
        "0x4Cf89ca06ad997bC732Dc876ed2A7F26a9E7f361",
        "0x4D2eE5DAe46C86DA2FF521F7657dad98834f97b8",
        "0x4Fabb145d64652a948d72533023f6E7A623C7C53",
        "0x4a527d8fc13C5203AB24BA0944F4Cb14658D1Db6",
        "0x4a615bB7166210CCe20E6642a6f8Fb5d4D044496",
        "0x4b13A8a95Da56773312cA0d4e0670530aa700FcF",
        "0x4eED0fa8dE12D5a86517f214C2f11586Ba2ED88D",
        "0x508df5aa4746bE37b5b6A69684DfD8BDC322219d",
        "0x50DE6856358Cc35f3A9a57eAAA34BD4cB707d2cd",
        "0x5150956E082C748Ca837a5dFa0a7C10CA4697f9c",
        "0x515d7E9D75E2b76DB60F8a051Cd890eBa23286Bc",
        "0x51DB5Ad35C671a87207d88fC11d593AC0C8415bd",
        "0x5218E472cFCFE0b64A064F055B43b4cdC9EfD3A6",
        "0x539F3615C1dBAfa0D008d87504667458acBd16Fa",
        "0x53Bd789F2cDb846b227d8ffc7B46eD4263231FDf",
        "0x55091eE4c62cdCF7bFB6E0f7F78447F8f7b44269",
        "0x557B933a7C2c45672B610F8954A3deB39a51A8Ca",
        "0x56860dbf9437c7109E1B3f66c00C68D33eE12A50",
        "0x579CEa1889991f68aCc35Ff5c3dd0621fF29b0C9",
        "0x58A3520D738B268c2353ECeE518A1AD8e28E4AE5",
        "0x594207C791afd06a8D087d84D99d1DA53CCbD45F",
        "0x59E9261255644c411AfDd00bD89162d09D862e38",
        "0x5Eaa69B29f99C84Fe5dE8200340b4e9b4Ab38EaC",
        "0x5EeAA2DCb23056F4E8654a349E57eBE5e76b5e6e",
        "0x5adc961D6AC3f7062D2eA45FEFB8D8167d44b190",
        "0x5d285F735998F36631F678FF41fb56A10A4d0429",
        "0x607F4C5BB672230e8672085532f7e901544a7375",
        "0x61107a409fFFe1965126aa456Af679719695C69C",
        "0x6149C26Cd2f7b5CCdb32029aF817123F6E37Df5B",
        "0x62Dc4817588d53a056cBbD18231d91ffCcd34b2A",
        "0x6339bd92EaA3Cb8e629B06449e08b90581a33ceA",
        "0x6399C842dD2bE3dE30BF99Bc7D1bBF6Fa3650E70",
        "0x63B8b7d4A3EFD0735c4BFFBD95B332a55e4eB851",
        "0x63b4f3e3fa4e438698CE330e365E831F7cCD1eF4",
        "0x6425c6BE902d692AE2db752B3c268AFAdb099D3b",
        "0x657B83A0336561C8f64389a6f5aDE675C04b0C3b",
        "0x65fC94d99Cb301C5630c485D312e6Ff5EDdE13d0",
        "0x66d28cb58487a7609877550E1a34691810A6b9FC",
        "0x66fD97a78d8854fEc445cd1C80a07896B0b4851f",
        "0x6B175474E89094C44Da98b954EedeAC495271d0F",
        "0x6B4c7A5e3f0B99FCD83e9c089BDDD6c7FCe5c611",
        "0x6D0F5149c502faf215C89ab306ec3E50b15e2892",
        "0x6DC02164d75651758aC74435806093E421b64605",
        "0x6be61833FC4381990e82D7D4a9F4c9B3F67eA941",
        "0x6c972b70c533E2E045F333Ee28b9fFb8D717bE69",
        "0x6e9730EcFfBed43fD876A264C982e254ef05a0DE",
        "0x71dc40668682a124231301414167E4CF7f55383C",
        "0x721A1B990699eE9D90b6327FaaD0A3E840aE8335",
        "0x725C263e32c72dDC3A19bEa12C5a0479a81eE688",
        "0x73627974adEa82397bcf7fac5848207CCE88938d",
        "0x73C9275c3a2Dd84b5741fD59AEbF102C91Eb033F",
        "0x740623d2c797b7D8D1EcB98e9b4Afcf99Ec31E14",
        "0x76c5449F4950f6338A393F53CdA8b53B0cd3Ca3a",
        "0x7777777777697cFEECF846A76326dA79CC606517",
        "0x77E9618179820961eE99a988983BC9AB41fF3112",
        "0x77dcE26c03a9B833fc2D7C31C22Da4f42e9d9582",
        "0x7815bDa662050D84718B988735218CFfd32f75ea",
        "0x7866E48C74CbFB8183cd1a929cd9b95a7a5CB4F4",
        "0x7A58c0Be72BE218B41C608b7Fe7C5bB630736C71",
        "0x7B69D465c0F9FB22AffAE56aa86149973e9B0966",
        "0x7Cfea0DD176651E7B5a1CeD9c4fAf8Ee295315FD",
        "0x7D92a06808B4c4833623F809218ed403e4A85FE1",
        "0x7aE1D57b58fA6411F32948314BadD83583eE0e8C",
        "0x7dE91B204C1C737bcEe6F000AAA6569Cf7061cb7",
        "0x7e291890B01E5181f7ecC98D79ffBe12Ad23df9e",
        "0x7e7E112A68d8D2E221E11047a72fFC1065c38e1a",
        "0x7e8539D1E5cB91d63E46B8e188403b3f262a949B",
        "0x7eaF9C89037e4814DC0d9952Ac7F888C784548DB",
        "0x8185Bc4757572Da2a610f887561c32298f1A5748",
        "0x83e6f1E41cdd28eAcEB20Cb649155049Fac3D5Aa",
        "0x84Bb947fcEdba6B9C7DCEad42dF07e113bb03007",
        "0x853d955aCEf822Db058eb8505911ED77F175b99e",
        "0x8564653879a18C560E7C0Ea0E084c516C62F5653",
        "0x87761e886399EF8e1624cb0DB3230B075a322c88",
        "0x8b0E42F366bA502d787BB134478aDfAE966C8798",
        "0x8c6Fa66c21aE3fC435790E451946a9Ea82E6e523",
        "0x8f8221aFbB33998d8584A2B05749bA73c37a938a",
        "0x9040e237C3bF18347bb00957Dc22167D0f2b999d",
        "0x9196E18Bc349B1F64Bc08784eaE259525329a1ad",
        "0x91dFbEE3965baAEE32784c2d546B7a0C62F268c9",
        "0x923b83c26B3809d960fF80332Ed00aA46D7Ed375",
        "0x92CfbEC26C206C90aeE3b7C66A9AE673754FaB7e",
        "0x92E187a03B6CD19CB6AF293ba17F2745Fd2357D5",
        "0x9506d37f70eB4C3d79C398d326C871aBBf10521d",
        "0x964291d2D0a7e3477a8a06ee745F3cD8E3d0B375",
        "0x96610186F3ab8d73EBEe1CF950C750f3B1Fb79C2",
        "0x967da4048cD07aB37855c090aAF366e4ce1b9F48",
        "0x9A54A39a8d78cD6031636628A11C890124b1b5cf",
        "0x9C2dc0c3CC2BADdE84B0025Cf4df1c5aF288D835",
        "0x9Ed8e7C9604790F7Ec589F99b94361d8AAB64E5E",
        "0x9F9913853f749b3fE6D6D4e16a1Cc3C1656B6D51",
        "0x9b31bb425D8263fA1b8B9d090b83CF0C31665355",
        "0x9cD39dA8f25ec50cF2Ee260e464aC23EA23F6bb0",
        "0x9cF77be84214beb066F26a4ea1c38ddcc2AFbcf7",
        "0x9fa69536d1cda4A04cFB50688294de75B505a9aE",
        "0xA01199c61841Fce3b3daFB83FeFC1899715c8756",
        "0xA3a7CBA479dF86C7F866280b90Ebc3B25f2371F0",
        "0xA87135285Ae208e22068AcDBFf64B11Ec73EAa5A",
        "0xAA2ce7Ae64066175E0B90497CE7d9c190c315DB4",
        "0xAC51066d7bEC65Dc4589368da368b212745d63E8",
        "0xAF9dB9E362e306688AF48c4ACB9618C06db38Ac3",
        "0xAa4e3edb11AFa93c41db59842b29de64b72E355B",
        "0xAc809cdf43a36acbD6D4e6E1676CA56aD8438E28",
        "0xAcfa209Fb73bF3Dd5bBfb1101B9Bc999C49062a5",
        "0xB1f66997A5760428D3a87D68b90BfE0aE64121cC",
        "0xB9964c8B9C48800678e72b2fe7B9B365d3D0019d",
        "0xBDFA65533074B0b23EbC18c7190BE79Fa74b30c2",
        "0xBae5F2D8a1299E5c4963eaff3312399253f27Ccb",
        "0xBc17729fDf562723f0267F79FF25aDE441056d87",
        "0xBeBdab6DA046Bc49ffBb61fbD7b33157Eb270D05",
        "0xC03841B5135600312707d39Eb2aF0D2aD5d51A91",
        "0xC28e931814725BbEB9e670676FaBBCb694Fe7DF2",
        "0xC36824905dfF2eAAEE7EcC09fCC63abc0af5Abc5",
        "0xC52C326331E9Ce41F04484d3B5E5648158028804",
        "0xC888A0Ab4831A29e6cA432BaBf52E353D23Db3c2",
        "0xCC4304A31d09258b0029eA7FE63d032f52e44EFe",
        "0xCF3C8Be2e2C42331Da80EF210e9B1b307C03d36A",
        "0xCb4e8CafEDa995da5cEdfda5205BD5664a12b848",
        "0xCc0014cCb39F6e86b1BE0f17859A783B6722722F",
        "0xCdeee767beD58c5325f68500115d4B722b3724EE",
        "0xD0660cD418a64a1d44E9214ad8e459324D8157f1",
        "0xD0Cd466b34A24fcB2f87676278AF2005Ca8A78c4",
        "0xD478161C952357F05f0292B56012Cd8457F1cfbF",
        "0xD7D8f3b8Bc8bC48d3AcC37879EABA7b85889FA52",
        "0xDA9FDAb21bC4A5811134A6E0Ba6CA06624e67c07",
        "0xE1D7C7a4596B038CEd2A84bF65B8647271C53208",
        "0xE2dc070524A6e305ddB64d8513DC444B6a1ec845",
        "0xE4AE84448DB5CFE1DaF1e6fb172b469c161CB85F",
        "0xE4CFE9eAa8Cdb0942A80B7bC68fD8Ab0F6D44903",
        "0xE4f726Adc8e89C6a6017F01eadA77865dB22dA14",
        "0xE51b8Ab09008285a0380Dd2680cD9Dd5e13924D3",
        "0xE7f58A92476056627f9FdB92286778aBd83b285F",
        "0xEA1ea0972fa092dd463f2968F9bB51Cc4c981D71",
        "0xEA26c4aC16D4a5A106820BC8AEE85fd0b7b2b664",
        "0xEF53462838000184F35f7D991452e5f25110b207",
        "0xEbEef419BB5A347E3D98f7D2168055214d12cBDb",
        "0xEc7D3E835dA3F6118079fA9a236b267D044FD7cA",
        "0xEd04915c23f00A313a544955524EB7DBD823143d",
        "0xEfc1C73A3D8728Dc4Cf2A18ac5705FE93E5914AC",
        "0xF2f9A7e93f845b3ce154EfbeB64fB9346FCCE509",
        "0xF3D6Af45C6dFeC43216CC3347Ea91fEfBa0849D1",
        "0xF519381791C03DD7666C142D4E49Fd94d3536011",
        "0xF5cFBC74057C610c8EF151A439252680AC68c6DC",
        "0xF70a642bD387F94380fFb90451C2c81d4Eb82CBc",
        "0xFD9cd8c0D18cD7e06958F3055e0Ec3ADbdba0B17",
        "0xFa14Fa6958401314851A17d6C5360cA29f74B57B",
        "0xFbbE9b1142C699512545f47937Ee6fae0e4B0aA9",
        "0xFd09911130e6930Bf87F2B0554c44F400bD80D3e",
        "0xFf44b937788215ecA197BAaf9AF69dbdC214aa04",
        "0xa0246c9032bC3A600820415aE600c6388619A14D",
        "0xa12D7e5319f5b43476eF19D1569E10097caCdFE2",
        "0xa1d6Df714F91DeBF4e0802A542E13067f31b8262",
        "0xa283aA7CfBB27EF0cfBcb2493dD9F4330E0fd304",
        "0xa5e48a6E56e164907263e901B98D9b11CCB46C47",
        "0xa7DE087329BFcda5639247F96140f9DAbe3DeED1",
        "0xaB37e1358b639Fd877f015027Bb62d3ddAa7557E",
        "0xaeF4F02E31CdbF007f8D98da4aE365188A0E9eCC",
        "0xb26C4B3Ca601136Daf98593feAeff9E0CA702a8D",
        "0xb31eF9e52d94D4120eb44Fe1ddfDe5B4654A6515",
        "0xb3214d4Af8af68e56A4716f7538e57C5f0ef622c",
        "0xb3ED706B564BBa9CAB64042f4e1b391bE7BEbCe5",
        "0xb453f1f2EE776dAF2586501361c457dB70e1ca0F",
        "0xb753428af26E81097e7fD17f40c88aaA3E04902c",
        "0xb9892F9A892f3e251fc58B9076c56aDD528eb8A6",
        "0xbA6B0dbb2bA8dAA8F5D6817946393Aef8D3A4487",
        "0xbBa6C7c7d673c48d90069ad2e9d2fE587fcB6bc3",
        "0xbcD4b7dE6fde81025f74426D43165a5b0D790Fdd",
        "0xbd1848e1491d4308Ad18287A745DD4DB2A4BD55B",
        "0xc12d099be31567add4e4e4d0D45691C3F58f5663",
        "0xc17fbe1d709dDf6C0B6665Dd0591046815AC7554",
        "0xc1f976B91217E240885536aF8b63bc8b5269a9BE",
        "0xc55c2175E90A46602fD42e931f62B3Acc1A013Ca",
        "0xc8D3DCb63C38607Cb0c9d3F55E8eccE628A01C36",
        "0xc96DF921009B790dfFcA412375251ed1A2b75c60",
        "0xcAaa93712BDAc37f736C323C93D4D5fDEFCc31CC",
        "0xcb86c6A22CB56B6cf40CaFEDb06BA0DF188a416E",
        "0xceb286C9604c542d3cc08b41AA6C9675B078A832",
        "0xd0345D30FD918D7682398ACbCdf139C808998709",
        "0xd080f46d7781a6C82B3Dd74A223B73242884E7e6",
        "0xd4342a57eCf2Fe7ffA37c33cb8f63b1500e575E6",
        "0xd714d91A169127e11D8FAb3665d72E8b7ef9Dbe2",
        "0xd7c302fc3ac829C7E896a32c4Bd126f3e8Bd0a1f",
        "0xd7f0cC50AD69408aE58be033F4f85D2367C2e468",
        "0xd8B110BeEe01E74DBa9Be687Fc247c550A41CFfe",
        "0xd9b312D77Bc7BEd9B9CecB56636300bED4Fe5Ce9",
        "0xdAC17F958D2ee523a2206206994597C13D831ec7",
        "0xdacD69347dE42baBfAEcD09dC88958378780FB62",
        "0xdfD8D604951eBF1b2297285F1B68de140C43992b",
        "0xe0B9a2C3E9f40CF74B2C7F591B2b0CCa055c3112",
        "0xe3818504c1B32bF1557b16C238B2E01Fd3149C17",
        "0xe63d6B308BCe0F6193AeC6b7E6eBa005f41e36AB",
        "0xe7976c4Efc60d9f4C200Cc1bCEF1A1e3B02c73e7",
        "0xeF6e45af9a422c5469928F927ca04ed332322e2e",
        "0xea5f88E54d982Cbb0c441cde4E79bC305e5b43Bc",
        "0xee573a945B01B788B9287CE062A0CFC15bE9fd86",
        "0xf009f5531dE69067435e32c4b9D36077F4C4A673",
        "0xf16e81dce15B08F326220742020379B855B87DF9",
        "0xf1F508c7C9f0d1b15a76fbA564eEf2d956220cf7",
        "0xf1f5De69C9C8D9BE8a7B01773Cc1166D4Ec6Ede2",
        "0xf3dcbc6D72a4E1892f7917b7C43b74131Df8480e",
        "0xf4CD3d3Fda8d7Fd6C5a500203e38640A70Bf9577",
        "0xf604D1e51122592E0bABe63ac334C0E647222F2D",
        "0xfAd45E47083e4607302aa43c65fB3106F1cd7607",
        "0xfB7B4564402E5500dB5bB6d63Ae671302777C75a",
        "0xfF20817765cB7f73d4bde2e66e067E58D11095C2",
        "0xfd8971d5E8E1740cE2d0A84095fCA4De729d0c16",
        "0xff2b3353c3015E9f1FBF95B9Bda23F58Aa7cE007",
        "0xff56Cc6b1E6dEd347aA0B7676C85AB0B3D08B0FA"
      ]
    },
    {
      "type": "basic",
      "address": "0x55F089d5f6aeDfdACBD5E3aCB0e8F31FBAb44088",
      "tokens": [
        "0x2260FAC5E5542a773Aa44fBCfeDf7C193bc2C599",
        "0x3432B6A60D23Ca0dFCa7761B7ab56459D9C964D0",
        "0x6B175474E89094C44Da98b954EedeAC495271d0F",
        "0x853d955aCEf822Db058eb8505911ED77F175b99e",
        "0xA0b86991c6218b36c1d19D4a2e9Eb0cE3606eB48",
        "0xdAC17F958D2ee523a2206206994597C13D831ec7",
        "ETH"
      ]
    },
    {
      "type": "any",
      "address": "0x5650C49D662cb83666aB0FAD224453B603179D2A",
      "tokens": ["0x37613D64258c0FE09d5E53EeCb091DA5b8fA8707"]
    },
    {
      "type": "any",
      "address": "0x57e8283743B169855248c1DE250B921336096677",
      "tokens": ["0x15Ee120fD69BEc86C1d38502299af7366a41D1a6"]
    },
    {
      "type": "basic",
      "address": "0x57ed6BD35a6CE815079855CD0b21331d1D5D0A0e",
      "tokens": [
        "0x2260FAC5E5542a773Aa44fBCfeDf7C193bc2C599",
        "0x6B3595068778DD592e39A122f4f5a5cF09C90fE2",
        "0xA0b86991c6218b36c1d19D4a2e9Eb0cE3606eB48",
        "0xdAC17F958D2ee523a2206206994597C13D831ec7",
        "ETH"
      ]
    },
    {
      "type": "any",
      "address": "0x58a547Ed09684ac2A688610d5Caf8e8968b51908",
      "tokens": ["0xc813EA5e3b48BEbeedb796ab42A30C5599b01740"]
    },
    {
      "type": "any",
      "address": "0x58c1BBb508e96CfEC1787Acf6Afe1C7008A5B064",
      "tokens": ["0x4Cf89ca06ad997bC732Dc876ed2A7F26a9E7f361"]
    },
    {
      "type": "any",
      "address": "0x59d1bF15E3340DaE7a5d893CC2296E2D939DAACd",
      "tokens": ["0xce20BB92CCF9BbF5091ef85649E71E552819AD8c"]
    },
    {
      "type": "any",
      "address": "0x5A33869045db8A6a16c9f351293501CFD92cf7ed",
      "tokens": ["0x47b9F01B16E9C9cb99191DCA68c9cc5bF6403957"]
    },
    {
      "type": "any",
      "address": "0x5a4fb10e7C4Cbb9a2b9d9A942f9a875EbD3489ea",
      "tokens": ["0x420412E765BFa6d85aaaC94b4f7b708C89be2e2B"]
    },
    {
      "type": "any",
      "address": "0x5Cb4B462cA075558eF0343db6b55F590e47482E4",
      "tokens": ["0xA31B1767e09f842ECFd4bc471Fe44F830E3891AA"]
    },
    {
      "type": "any",
      "address": "0x5CDD7cD69cEdb9b56b8CA47F844A0dE16d8b5761",
      "tokens": ["0xD6123271F980D966B00cA4FCa6C2c021f05e2E73"]
    },
    {
      "type": "any",
      "address": "0x5CF33b95B162D0Ac497e4bf47d757Ecb452d9062",
      "tokens": ["0x5150956E082C748Ca837a5dFa0a7C10CA4697f9c"]
    },
    {
      "type": "any",
      "address": "0x5d47bAbA0d66083C52009271faF3F50DCc01023C",
      "tokens": ["0x85Ffb35957203dfD12061eAeCD708dB623Bd567C"]
    },
    {
      "type": "any",
      "address": "0x5d5530eb3147152FE78d5C4bFEeDe054c8d1442A",
      "tokens": ["0x8A65B987D9813f0a97446eDa0dE918b2573Ae406"]
    },
    {
      "type": "any",
      "address": "0x5f1C76b7a90D88EE5BADa971a28AAEF514719dBF",
      "tokens": ["0xc17fbe1d709dDf6C0B6665Dd0591046815AC7554"]
    },
    {
      "type": "any",
      "address": "0x5fCB9de282Af6122ce3518CDe28B7089c9F97b26",
      "tokens": ["0xfF3Ac80c1caA08Cbd43a7e90d20c398d54C7342f"]
    },
    {
      "type": "any",
      "address": "0x5fd564518A71AAB9B1D0Ac6D5825bbBC46a5845e",
      "tokens": ["0xDE5ed76E7c05eC5e4572CfC88d1ACEA165109E44"]
    },
    {
      "type": "any",
      "address": "0x5fE67350E9D2AaB2570Ff86b48509a18cfd7b08C",
      "tokens": ["0x7A73839bd0e5cdED853cB01aa9773F8989381065"]
    },
    {
      "type": "any",
      "address": "0x623332A33Ae3a8fC9B121322C72550Decc0eD81C",
      "tokens": ["0xdf09a216Fac5ADC3e640Db418C0b956076509503"]
    },
    {
      "type": "any",
      "address": "0x6362496Bef53458b20548a35A2101214Ee2BE3e0",
      "tokens": ["0x8290333ceF9e6D528dD5618Fb97a76f268f3EDD4"]
    },
    {
      "type": "any",
      "address": "0x63F366892B53EE0F0E31d6590EA191ae9A0a62e9",
      "tokens": ["0x286C0936c7Eaf6651099Ab5DAb9ee5A6cB5d229D"]
    },
    {
      "type": "any",
      "address": "0x6474239b1a83cEB3789CD8dDb2218e6f5C6840Dd",
      "tokens": ["0x93Dede06AE3B5590aF1d4c111BC54C3f717E4b35"]
    },
    {
      "type": "any",
      "address": "0x6496994241804D7fE2b032901931e03bCD82301F",
      "tokens": ["0xab167E816E4d76089119900e941BEfdfA37d6b32"]
    },
    {
      "type": "any",
      "address": "0x64Ee4f41A15D6c431AB6607d4e95462169d50f6C",
      "tokens": ["0x0adA190c81b814548ddC2F6AdC4a689ce7C1FE73"]
    },
    {
      "type": "any",
      "address": "0x6562E5791Da22950c959b8C2febCFbcA15AE520c",
      "tokens": ["0x57b59f981730c6257dF57cF6F0D98283749A9Eeb"]
    },
    {
      "type": "any",
      "address": "0x6574e2c013171Cd50A6d34e588906047A0d12F2c",
      "tokens": ["0x0AAbCC65Ef352AD84b1326dF188c95b6Ab856c1C"]
    },
    {
      "type": "basic",
      "address": "0x65e64963b755043CA4FFC88029FfB8305615EeDD",
      "tokens": [
        "0x0bc529c00C6401aEF6D220BE8C6Ea1667F6Ad93e",
        "0x514910771AF9Ca656af840dff83E8264EcF986CA",
        "0x6B175474E89094C44Da98b954EedeAC495271d0F",
        "0xdAC17F958D2ee523a2206206994597C13D831ec7",
        "ETH"
      ]
    },
    {
      "type": "basic",
      "address": "0x668b9734FfE9eE8a01d4Ade3362De71E8989EA87",
      "tokens": [
        "0x06a87F6aFEc4a739c367bEF69eEfE383D27106bd",
        "0x0E29e5AbbB5FD88e28b2d355774e73BD47dE3bcd",
        "0x1117aC6Ad6Cdf1A3BC543baD3B133724620522d5",
        "0x16ba8Efe847EBDFef99d399902ec29397D403C30",
        "0x20a8CEC5fffea65Be7122BCaB2FFe32ED4Ebf03a",
        "0x21fb4DD8C500BE1A9BA27F827217E477217D6225",
        "0x28fDA76721a8077A5dE802Ab0212849B8c38429E",
        "0x29C56E7CB9C840d2b2371b17e28BaB44AD3c3ead",
        "0x327673aE6B33Bd3d90f0096870059994f30Dc8AF",
        "0x4CC19356f2D37338b9802aa8E8fc58B0373296E7",
        "0x594207C791afd06a8D087d84D99d1DA53CCbD45F",
        "0x6149C26Cd2f7b5CCdb32029aF817123F6E37Df5B",
        "0x616ef40D55C0D2c506f4d6873Bda8090b79BF8fC",
        "0x6243d8CEA23066d098a15582d81a598b4e8391F4",
        "0x62Dc4817588d53a056cBbD18231d91ffCcd34b2A",
        "0x66fD97a78d8854fEc445cd1C80a07896B0b4851f",
        "0x6c972b70c533E2E045F333Ee28b9fFb8D717bE69",
        "0x71dc40668682a124231301414167E4CF7f55383C",
        "0x7815bDa662050D84718B988735218CFfd32f75ea",
        "0x8f8221aFbB33998d8584A2B05749bA73c37a938a",
        "0xA5Ef74068d04ba0809B7379dD76Af5Ce34Ab7C57",
        "0xAa4e3edb11AFa93c41db59842b29de64b72E355B",
        "0xBc17729fDf562723f0267F79FF25aDE441056d87",
        "0xD528cf2E081f72908e086F8800977df826B5a483",
        "0xDA9FDAb21bC4A5811134A6E0Ba6CA06624e67c07",
        "0xE1D7C7a4596B038CEd2A84bF65B8647271C53208",
        "0xE4AE84448DB5CFE1DaF1e6fb172b469c161CB85F",
        "0xE4CFE9eAa8Cdb0942A80B7bC68fD8Ab0F6D44903",
        "0xE7f58A92476056627f9FdB92286778aBd83b285F",
        "0xEbEef419BB5A347E3D98f7D2168055214d12cBDb",
        "0xF0c5831EC3Da15f3696B4DAd8B21c7Ce2f007f28",
        "0xFD9cd8c0D18cD7e06958F3055e0Ec3ADbdba0B17",
        "0xFeea0bDd3D07eb6FE305938878C0caDBFa169042",
        "0xb26C4B3Ca601136Daf98593feAeff9E0CA702a8D",
        "0xb9EF770B6A5e12E45983C5D80545258aA38F3B78",
        "0xbd1848e1491d4308Ad18287A745DD4DB2A4BD55B",
        "0xc690F7C7FcfFA6a82b79faB7508c466FEfdfc8c5",
        "0xcAaa93712BDAc37f736C323C93D4D5fDEFCc31CC",
        "0xd714d91A169127e11D8FAb3665d72E8b7ef9Dbe2",
        "0xd7c302fc3ac829C7E896a32c4Bd126f3e8Bd0a1f",
        "0xd7f0cC50AD69408aE58be033F4f85D2367C2e468",
        "0xd9b312D77Bc7BEd9B9CecB56636300bED4Fe5Ce9",
        "0xeDF6568618A00C6F0908Bf7758A16F76B6E04aF9",
        "0xf009f5531dE69067435e32c4b9D36077F4C4A673",
        "0xf16e81dce15B08F326220742020379B855B87DF9",
        "0xf604D1e51122592E0bABe63ac334C0E647222F2D",
        "0xfAd45E47083e4607302aa43c65fB3106F1cd7607",
        "0xfF20817765cB7f73d4bde2e66e067E58D11095C2"
      ]
    },
    {
      "type": "any",
      "address": "0x685b63CFE0179b3EFb70A01dCb1D648549AA192d",
      "tokens": ["0x3432B6A60D23Ca0dFCa7761B7ab56459D9C964D0"]
    },
    {
      "type": "any",
      "address": "0x6B26780e74Cfc64B88c9e1ebc33fFAe29c1679eA",
      "tokens": ["0x147faF8De9d8D8DAAE129B187F0D02D819126750"]
    },
    {
      "type": "any",
      "address": "0x6b289CCeAA8639e3831095D75A3e43520faBf552",
      "tokens": ["0x26FA3fFFB6EfE8c1E69103aCb4044C26B9A106a9"]
    },
    {
      "type": "any",
      "address": "0x6d8516BAaBc086C725707C8F630CcD6D7A68AC3F",
      "tokens": ["0xc87f0a3F3671F7d01278625561dc6e284B62daE9"]
    },
    {
      "type": "any",
      "address": "0x6e264D4f2f7810CB82B9B73d6310e73c88be0bfF",
      "tokens": ["0x92B914f1DDcBb1D117a718E83C9ED7eB32fc44d1"]
    },
    {
      "type": "any",
      "address": "0x6Ed2b2ac055bd755c3A30Fb9c039922859CaA0ba",
      "tokens": ["0x953Cd009a490176FcEB3a26b9753e6F01645ff28"]
    },
    {
      "type": "any",
      "address": "0x6feFd97F328342a8A840546A55FDcfEe7542F9A8",
      "tokens": ["0xEe9E5eFF401ee921b138490d00CA8D1F13f67A72"]
    },
    {
      "type": "any",
      "address": "0x701e67fa3121343C866dFE69Ae98534265B65bFa",
      "tokens": ["0x4a621d9f1b19296d1C0f87637b3A8D4978e9bf82"]
    },
    {
      "type": "any",
      "address": "0x702D161Ed480e4a367a5810a6086074B791cf6A0",
      "tokens": ["0xDf49C9f599A0A9049D97CFF34D0C30E468987389"]
    },
    {
      "type": "any",
      "address": "0x70fB6418bBB2863e341286b72535bD4828Ec863a",
      "tokens": ["0xBA41Ddf06B7fFD89D1267b5A93BFeF2424eb2003"]
    },
    {
      "type": "any",
      "address": "0x712052F807eafd1A27D7350e33F0A6C500385Df4",
      "tokens": ["0x1A4b46696b2bB4794Eb3D4c26f1c55F9170fa4C5"]
    },
    {
      "type": "any",
      "address": "0x739ca6D71365a08f584c8FC4e1029045Fa8ABC4B",
      "tokens": ["0x6B175474E89094C44Da98b954EedeAC495271d0F"]
    },
    {
      "type": "any",
      "address": "0x758d08864fB6cCE3062667225ca10b8F00496cc2",
      "tokens": ["0x9Ac59862934ebc36072D4D8ADA37c62373A13856"]
    },
    {
      "type": "any",
      "address": "0x76ce14947f74A2664700e68452fe9166174AF9Ab",
      "tokens": ["0xE9cB6838902CCF711f16a9EA5A1170F8e9853C02"]
    },
    {
      "type": "any",
      "address": "0x76FBa02e148cab052f86dc1d8f4b10e64EfC7046",
      "tokens": ["0x6CD13E1856286dE773a435C8Ba93A7C73A04F82d"]
    },
    {
      "type": "any",
      "address": "0x7761a5e95C96ff0d68dAf5eF2f94741229b36b50",
      "tokens": ["0xF0d33BeDa4d734C72684b5f9abBEbf715D0a7935"]
    },
    {
      "type": "any",
      "address": "0x77c62e549ca46EF8Dd5Edc052B1edC783F60A400",
      "tokens": ["0xFeea0bDd3D07eb6FE305938878C0caDBFa169042"]
    },
    {
      "type": "any",
      "address": "0x782617249085AA28A367fEB49CF811434660cEE5",
      "tokens": ["0xc6DdDB5bc6E61e0841C54f3e723Ae1f3A807260b"]
    },
    {
      "type": "any",
      "address": "0x790CFDc6aB2e0eE45a433aAC5434F183BE1f6A20",
      "tokens": ["0x88536C9B2C4701b8dB824e6A16829D5B5Eb84440"]
    },
    {
      "type": "any",
      "address": "0x79820e2b9C55574504B1EF5b606dC81C526f3CFA",
      "tokens": ["0xb683D83a532e2Cb7DFa5275eED3698436371cc9f"]
    },
    {
      "type": "any",
      "address": "0x7a02492bAa66B0b8266a6d25Bbd6D8BA169296CC",
      "tokens": ["0x95b3497bBcCcc46a8F45F5Cf54b0878b39f8D96C"]
    },
    {
      "type": "any",
      "address": "0x7B7CAFA0d7E72fD10Df4e6F855dA9e2cA0c5F45D",
      "tokens": ["0x4FbB350052Bca5417566f188eB2EBCE5b19BC964"]
    },
    {
      "type": "any",
      "address": "0x7BEB05cf5681f402E762F8569c2Fc138a2172978",
      "tokens": ["0xdeFA4e8a7bcBA345F687a2f1456F5Edd9CE97202"]
    },
    {
      "type": "any",
      "address": "0x7D09a42045359Aa85488bC07D0ADa83E22d50017",
      "tokens": ["0x6911F552842236bd9E8ea8DDBB3fb414e2C5FA9d"]
    },
    {
      "type": "any",
      "address": "0x7EA2be2df7BA6E54B1A9C70676f668455E329d29",
      "tokens": ["0xA0b86991c6218b36c1d19D4a2e9Eb0cE3606eB48"]
    },
    {
      "type": "any",
      "address": "0x7f352fA977713019C484C58E9BDfB04910016871",
      "tokens": ["0xeDADeB5fAa413e6c8623461849DFD0B7C3790c32"]
    },
    {
      "type": "any",
      "address": "0x7F8BC696bEBbbd29255F871cBef55B74e8F10E57",
      "tokens": ["0x6E765D26388A17A6e86c49A8E41DF3F58aBcd337"]
    },
    {
      "type": "basic",
      "address": "0x7F923dB3d90047D75D078e29b1f8Eac03e30F761",
      "tokens": [
        "0x2260FAC5E5542a773Aa44fBCfeDf7C193bc2C599",
        "0x6B175474E89094C44Da98b954EedeAC495271d0F",
        "0xA0b86991c6218b36c1d19D4a2e9Eb0cE3606eB48",
        "0xdAC17F958D2ee523a2206206994597C13D831ec7",
        "ETH"
      ]
    },
    {
      "type": "any",
      "address": "0x7FC5670B2041d34414B0b2178Fc660b1E1faF801",
      "tokens": ["0x5a75A093747b72a0e14056352751eDF03518031d"]
    },
    {
      "type": "basic",
      "address": "0x80641af4A0e1dcD69d7EA75ceB8D661baa84297c",
      "tokens": [
        "0x226f7b842E0F0120b7E194D05432b3fd14773a9D",
        "0x3Dc7B06dD0B1f08ef9AcBbD2564f8605b4868EEA"
      ]
    },
    {
      "type": "any",
      "address": "0x80FD8E18cC59177B4dbD2FaE9c0efB8Bf87EDc1f",
      "tokens": ["0x05D3606d5c81EB9b7B18530995eC9B29da05FaBa"]
    },
    {
      "type": "any",
      "address": "0x818ec0A7Fe18Ff94269904fCED6AE3DaE6d6dC0b",
      "tokens": ["0x7968bc6a03017eA2de509AAA816F163Db0f35148"]
    },
    {
      "type": "basic",
      "address": "0x820A9eb227BF770A9dd28829380d53B76eAf1209",
      "tokens": [
        "0x03ab458634910AaD20eF5f1C8ee96F1D6ac54919",
        "0x06B884e60794Ce02AafAb13791B59A2e6A07442f",
        "0x06a87F6aFEc4a739c367bEF69eEfE383D27106bd",
        "0x0f7F961648aE6Db43C75663aC7E5414Eb79b5704",
        "0x16ba8Efe847EBDFef99d399902ec29397D403C30",
        "0x1A3496C18d558bd9C6C8f609E1B129f67AB08163",
        "0x1a7e4e63778B4f12a199C062f3eFdD288afCBce8",
        "0x1f19f83fC9a25F3C861260143E36c17706257986",
        "0x226f7b842E0F0120b7E194D05432b3fd14773a9D",
        "0x2791BfD60D232150Bff86b39B7146c0eaAA2BA81",
        "0x29127fE04ffa4c32AcAC0fFe17280ABD74eAC313",
        "0x2C31b10ca416b82Cec4c5E93c615ca851213d48D",
        "0x2D80f5F5328FdcB6ECeb7Cacf5DD8AEDaEC94e20",
        "0x31429d1856aD1377A8A0079410B297e1a9e214c2",
        "0x3301Ee63Fb29F863f2333Bd4466acb46CD8323E6",
        "0x3432B6A60D23Ca0dFCa7761B7ab56459D9C964D0",
        "0x34f797e7190C131cF630524655A618b5BD8738e7",
        "0x374CB8C27130E2c9E04F44303f3c8351B9De61C1",
        "0x3aFfCCa64c2A6f4e3B6Bd9c64CD2C969EFd1ECBe",
        "0x56A86d648c435DC707c8405B78e2Ae8eB4E60Ba4",
        "0x5F64Ab1544D28732F0A24F4713c2C8ec0dA089f0",
        "0x6B4c7A5e3f0B99FCD83e9c089BDDD6c7FCe5c611",
        "0x6e9730EcFfBed43fD876A264C982e254ef05a0DE",
        "0x73968b9a57c6E53d41345FD57a6E6ae27d6CDB2F",
        "0x7778360F035C589fCE2f4eA5786CbD8B36e5396B",
        "0x77dcE26c03a9B833fc2D7C31C22Da4f42e9d9582",
        "0x7aE0d42f23C33338dE15bFa89C7405c068d9dC0a",
        "0x808507121B80c02388fAd14726482e061B8da827",
        "0x8290333ceF9e6D528dD5618Fb97a76f268f3EDD4",
        "0x84d821F7FbDD595c4C4A50842913e6b1E07d7a53",
        "0x853d955aCEf822Db058eb8505911ED77F175b99e",
        "0xA5Ef74068d04ba0809B7379dD76Af5Ce34Ab7C57",
        "0xAa4e3edb11AFa93c41db59842b29de64b72E355B",
        "0xAcfa209Fb73bF3Dd5bBfb1101B9Bc999C49062a5",
        "0xBDFA65533074B0b23EbC18c7190BE79Fa74b30c2",
        "0xBc17729fDf562723f0267F79FF25aDE441056d87",
        "0xD0Cd466b34A24fcB2f87676278AF2005Ca8A78c4",
        "0xD533a949740bb3306d119CC777fa900bA034cd52",
        "0xE0aD1806Fd3E7edF6FF52Fdb822432e847411033",
        "0xb453f1f2EE776dAF2586501361c457dB70e1ca0F",
        "0xcAaa93712BDAc37f736C323C93D4D5fDEFCc31CC",
        "0xcb86c6A22CB56B6cf40CaFEDb06BA0DF188a416E",
        "0xceb286C9604c542d3cc08b41AA6C9675B078A832",
        "0xd52AAE39a2b5CC7812F7B9450EBB61DfEf702B15",
        "0xf16e81dce15B08F326220742020379B855B87DF9",
        "0xfF20817765cB7f73d4bde2e66e067E58D11095C2",
        "0xff56Cc6b1E6dEd347aA0B7676C85AB0B3D08B0FA",
        "ETH"
      ]
    },
    {
      "type": "any",
      "address": "0x826Ee16b4B401E84c76b48a2A81545cBb994A995",
      "tokens": ["0x9040e237C3bF18347bb00957Dc22167D0f2b999d"]
    },
    {
      "type": "any",
      "address": "0x827eD6FE802dB52970F0e36B709279E606e4F252",
      "tokens": ["0x7051faED0775f664a0286Af4F75ef5ed74e02754"]
    },
    {
      "type": "any",
      "address": "0x82f0B8B456c1A451378467398982d4834b6829c1",
      "tokens": ["0x32a7C02e79c4ea1008dD6564b35F131428673c41"]
    },
    {
      "type": "any",
      "address": "0x83102Ec9B8A4DbF2E6aA41f6E7C8B5863B800681",
      "tokens": ["0xF9C2B386FF5Df088AC717ab0010587bad3bC1ab1"]
    },
    {
      "type": "any",
      "address": "0x8323FCF06D58F49533Da60906D731c6a56626Fb2",
      "tokens": ["0xF063fE1aB7a291c5d06a86e14730b00BF24cB589"]
    },
    {
      "type": "any",
      "address": "0x84051Efb5e0c61AC1863B5de72Cd5bC3221870E4",
      "tokens": ["0x69570f3E84f51Ea70b7B68055c8d667e77735a25"]
    },
    {
      "type": "any",
      "address": "0x8497842420cFdbc97896C2353D75d89Fc8D5Be5D",
      "tokens": ["0x5f018e73C185aB23647c82bD039e762813877f0e"]
    },
    {
      "type": "any",
      "address": "0x84Ae7b0FF2Bc523969fB3162E04149A419196F4b",
      "tokens": ["0xcAfE001067cDEF266AfB7Eb5A286dCFD277f3dE5"]
    },
    {
      "type": "any",
      "address": "0x84e9a6F9D240FdD33801f7135908BfA16866939A",
      "tokens": ["0x0E5C8C387C5EBa2eCbc137aD012aeD5Fe729e251"]
    },
    {
      "type": "any",
      "address": "0x85009bcA4cd4C8F554c3C9a1c2f778Ec3Ce7fEb1",
      "tokens": ["0x2b95A1Dcc3D405535f9ed33c219ab38E8d7e0884"]
    },
    {
      "type": "any",
      "address": "0x86A298581388bc199e61BFeCDcA8eA22Cf6C0Da3",
      "tokens": ["0xD9A8bB44968F35282F1b91c353f77a61BaF31A4B"]
    },
    {
      "type": "basic",
      "address": "0x87bCB3038988ca2A89605fFa8f237FB78Df1c3Ae",
      "tokens": [
        "0x1a7e4e63778B4f12a199C062f3eFdD288afCBce8",
        "0xA0b86991c6218b36c1d19D4a2e9Eb0cE3606eB48",
        "ETH"
      ]
    },
    {
      "type": "any",
      "address": "0x884247ec9921195C1e722d5e8E812415BD8715d2",
      "tokens": ["0x97A3BD8a445cC187c6A751F392e15C3B2134D695"]
    },
    {
      "type": "basic",
      "address": "0x896be9f48b225154593A84b382d927F9d7Bc2361",
      "tokens": [
        "0x2260FAC5E5542a773Aa44fBCfeDf7C193bc2C599",
        "0x6B175474E89094C44Da98b954EedeAC495271d0F",
        "0xA0b86991c6218b36c1d19D4a2e9Eb0cE3606eB48",
        "0xdAC17F958D2ee523a2206206994597C13D831ec7",
        "ETH"
      ]
    },
    {
      "type": "any",
      "address": "0x8b92eA35171e29948Cc9e49c52AC8dB0549B7D6B",
      "tokens": ["0xAC57De9C1A09FeC648E93EB98875B212DB0d460B"]
    },
    {
      "type": "any",
      "address": "0x8BB9Cac776555E0Ac707024Ed729E5AACeAfBE72",
      "tokens": ["0x50D1c9771902476076eCFc8B2A83Ad6b9355a4c9"]
    },
    {
      "type": "any",
      "address": "0x8c62c65D65176b9d45Ab180E23eB5DaCC2E599a4",
      "tokens": ["0x09F098B155D561Fc9F7BcCc97038b7e3d20bAF74"]
    },
    {
      "type": "basic",
      "address": "0x8cC49FE67A4bD7a15674c4ffD4E969D94304BBbf",
      "tokens": [
        "0x0000000000085d4780B73119b644AE5ecd22b376",
        "0x2260FAC5E5542a773Aa44fBCfeDf7C193bc2C599",
        "0x6B175474E89094C44Da98b954EedeAC495271d0F",
        "0xA0b86991c6218b36c1d19D4a2e9Eb0cE3606eB48",
        "0xdAC17F958D2ee523a2206206994597C13D831ec7",
        "ETH"
      ]
    },
    {
      "type": "any",
      "address": "0x8CD309e14575203535EF120b5b0Ab4DDeD0C2073",
      "tokens": ["0xCe16A802725438AF9b4dcac00E7791E3D890E3b4"]
    },
    {
      "type": "any",
      "address": "0x8CE3dfcAe03beb7D2CAb25a1E1434C3791f45DD8",
      "tokens": ["0x4C2e59D098DF7b6cBaE0848d66DE2f8A4889b9C3"]
    },
    {
      "type": "any",
      "address": "0x8D34a11f49172C057d11833cF92AFF97F28Fc595",
      "tokens": ["0x95A1796437BAd6502d1c1cce165Cd76E522409a9"]
    },
    {
      "type": "any",
      "address": "0x8dFDC61c7c7551D0DEec950A2822eB59cddb8f59",
      "tokens": ["0x514910771AF9Ca656af840dff83E8264EcF986CA"]
    },
    {
      "type": "any",
      "address": "0x8e60d469A94E1be77668e8c9c55C498701870762",
      "tokens": ["0xCa76543Cf381ebBB277bE79574059e32108e3E65"]
    },
    {
      "type": "any",
      "address": "0x90F615bB7b2Def7Bd14C507f90ff42B6aCAcf86e",
      "tokens": ["0xAACa86B876ca011844b5798ECA7a67591A9743C8"]
    },
    {
      "type": "any",
      "address": "0x91827Bc11CB9bbeD7F4796393CD664Aff9C60f58",
      "tokens": ["0x6E98E5401ADCB0D76F4DEBfc3d794B3031F48790"]
    },
    {
      "type": "any",
      "address": "0x922D641a426DcFFaeF11680e5358F34d97d112E1",
      "tokens": ["0xd794DD1CAda4cf79C9EebaAb8327a1B0507ef7d4"]
    },
    {
      "type": "basic",
      "address": "0x923e0a17F49Fb03d936F2af2D59D379C615f5447",
      "tokens": [
        "0x2260FAC5E5542a773Aa44fBCfeDf7C193bc2C599",
        "0x3845badAde8e6dFF049820680d1F14bD3903a5d0",
        "0x5150956E082C748Ca837a5dFa0a7C10CA4697f9c",
        "0x6B175474E89094C44Da98b954EedeAC495271d0F",
        "ETH"
      ]
    },
    {
      "type": "any",
      "address": "0x92804831aC036Ca77D57Db8BBA0E522Cd35a8049",
      "tokens": ["0x6B175474E89094C44Da98b954EedeAC495271d0F"]
    },
    {
      "type": "any",
      "address": "0x937E077aBaEA52d3abf879c9b9d3f2eBd15BAA21",
      "tokens": ["0x327673aE6B33Bd3d90f0096870059994f30Dc8AF"]
    },
    {
      "type": "any",
      "address": "0x944A05c5acC46c9777ACA7d8dD92B048b1b6D3e0",
      "tokens": ["0xff56Cc6b1E6dEd347aA0B7676C85AB0B3D08B0FA"]
    },
    {
      "type": "any",
      "address": "0x95555E4e4CB2C094914aF53598eFf14b9340881f",
      "tokens": ["0x4691937a7508860F876c9c0a2a617E7d9E945D4B"]
    },
    {
      "type": "any",
      "address": "0x95dD59343a893637BE1c3228060EE6afBf6F0730",
      "tokens": ["0xf3Db5Fa2C66B7aF3Eb0C0b782510816cbe4813b8"]
    },
    {
      "type": "any",
      "address": "0x976cDc77E43667747E35C82A9477111259d0c6f0",
      "tokens": ["0xC86817249634ac209bc73fCa1712bBd75E37407d"]
    },
    {
      "type": "any",
      "address": "0x97Cd1CFE2ed5712660bb6c14053C0EcB031Bff7d",
      "tokens": ["0xd26fb114401Ec86887CD09F62eccd95fCf20B571"]
    },
    {
      "type": "basic",
      "address": "0x97cFFC8aaDC28cda8Ba901667222d6386A46f705",
      "tokens": ["0xC02aaA39b223FE8D0A0e5C4F27eAD9083C756Cc2"]
    },
    {
      "type": "any",
      "address": "0x981e360161a37dE663F232E6c800Fc6a56Fb536A",
      "tokens": ["0xC382e04099A435439725BB40647e2B32dC136806"]
    },
    {
      "type": "any",
      "address": "0x9833c643f387ecFB76AA8114546AD524703c66Fb",
      "tokens": ["0x3E5D9D8a63CC8a88748f229999CF59487e90721e"]
    },
    {
      "type": "any",
      "address": "0x986A4EA3679AFe15b5963A6Ec3437bE859279BC1",
      "tokens": ["0xd9adb7536E90660F601c5BFB15cB49BFa78cA0a6"]
    },
    {
      "type": "any",
      "address": "0x9889799f43a2EB9b34FBdd83bb840EAa42462a77",
      "tokens": ["0xE61776305003d700FBC8318da97806032a3b08ED"]
    },
    {
      "type": "any",
      "address": "0x99f7D752745f270E100233cC05768B4a12Bd09f0",
      "tokens": ["0x48592de8CdED16f6Bb56c896Fe1Affc37630889C"]
    },
    {
      "type": "any",
      "address": "0x9A046925f592513a9cA9eD214112e373f7971023",
      "tokens": ["0x6F66f3012E0210baBD2384e31863C30f70356237"]
    },
    {
      "type": "any",
      "address": "0x9a058058e14838ef83d25Df227C149AFf7DF8bD3",
      "tokens": ["0x3235B13708F178Af6F110dE7177ED5De10c1093d"]
    },
    {
      "type": "any",
      "address": "0x9A161F660053fE279E5c28D43622C480E8AEA96A",
      "tokens": ["0x305DE070488C8469dFAC957226c9c900c4BFbA22"]
    },
    {
      "type": "any",
      "address": "0x9b2f9F348425b1eF54c232F87eE7d4D570c1b552",
      "tokens": ["0xfAd45E47083e4607302aa43c65fB3106F1cd7607"]
    },
    {
      "type": "basic",
      "address": "0x9c1F1f8d03f5cca7a5D31b56D90c967B1D8cFAb7",
      "tokens": ["0xD533a949740bb3306d119CC777fa900bA034cd52"]
    },
    {
      "type": "any",
      "address": "0x9ea48018587fdf4B5857940171d3D32465B0B761",
      "tokens": ["0x5d30aD9C6374Bf925D0A75454fa327AACf778492"]
    },
    {
      "type": "any",
      "address": "0x9EBA16F6b7e8848e440922861123F0bee957002a",
      "tokens": ["0x297D33e17e61C2Ddd812389C2105193f8348188a"]
    },
    {
      "type": "any",
      "address": "0x9F47F313ACFd4bdC52F4373b493EaE7d5aC5b765",
      "tokens": ["0x3085154623F51b00Dedfc6Ceeb5197277A66B17B"]
    },
    {
      "type": "any",
      "address": "0x9Fb9a33956351cf4fa040f65A13b835A3C8764E3",
      "tokens": ["0x65Ef703f5594D2573eb71Aaf55BC0CB548492df4"]
    },
    {
      "type": "any",
      "address": "0xA01A715a1465150060ec881FDFbf02186072B5E8",
      "tokens": ["0x559b7bfC48a5274754b08819F75C5F27aF53D53b"]
    },
    {
      "type": "basic",
      "address": "0xA024856a51B1D8bFBbc78DDbc98e6d5b94dc24c4",
      "tokens": ["0xdAC17F958D2ee523a2206206994597C13D831ec7"]
    },
    {
      "type": "any",
      "address": "0xa097c96ACc9587D140AD8aEaAC13D9db2C6CC07f",
      "tokens": ["0xCd2828fc4D8E8a0eDe91bB38CF64B1a81De65Bf6"]
    },
    {
      "type": "any",
      "address": "0xa0EDa2D19211D108772711A3698C69f79673aEC8",
      "tokens": ["0xa52bfFAD02B1FE3f86A543a4e81962d3B3bB01A7"]
    },
    {
      "type": "any",
      "address": "0xA1388e73c51B37383B1Ab9dCe8317eF5A0349CC5",
      "tokens": ["0xC4398e483B178AC559b4fe665c6BCE70A179f80F"]
    },
    {
      "type": "any",
      "address": "0xA15A269a54f377292B2B0369cf10655b0F76D201",
      "tokens": ["0x0D97Fee619d955509e54B046c9992B6E9F5B0630"]
    },
    {
      "type": "any",
      "address": "0xA1Ae26219565370fCFEa073249309D117D805c39",
      "tokens": ["0x4B1E80cAC91e2216EEb63e29B957eB91Ae9C2Be8"]
    },
    {
      "type": "any",
      "address": "0xA4d4b757EeD23AbbebD747Da2c75e9288Ff1785b",
      "tokens": ["0x56694577564FdD577a0ABB20FE95C1E2756C2a11"]
    },
    {
      "type": "any",
      "address": "0xa4FFfc757e8c4F24E7b209C033c123D20983Ad40",
      "tokens": ["0x3F6D1649A1366b0E82173D33e365953f9F1Cc84C"]
    },
    {
      "type": "any",
      "address": "0xA5432cbF7097C4E3536731dEc837e3fA676b38C3",
      "tokens": ["0x6B3595068778DD592e39A122f4f5a5cF09C90fE2"]
    },
    {
      "type": "any",
      "address": "0xa65225a7C67d7E44183dBCc04eBd434Bc32F29b7",
      "tokens": ["0x06B884e60794Ce02AafAb13791B59A2e6A07442f"]
    },
    {
      "type": "any",
      "address": "0xa65779AA9a29af831DA49c48899e7146934905C7",
      "tokens": ["0x967da4048cD07aB37855c090aAF366e4ce1b9F48"]
    },
    {
      "type": "any",
      "address": "0xA6e822E865fBE37D6EBC6d721947aFbBd9F95C19",
      "tokens": ["0xC741f06082AA47F93729070aD0dD95E223Bda091"]
    },
    {
      "type": "any",
      "address": "0xa71353Bb71DdA105D383B02fc2dD172C4D39eF8B",
      "tokens": ["0x0f17BC9a994b87b5225cFb6a2Cd4D667ADb4F20B"]
    },
    {
      "type": "any",
      "address": "0xA753eFA27EFd65A456295078eD606306c52c2EbF",
      "tokens": ["0x893700A1a86EE68B92536bf6fd4d3200d7369F7d"]
    },
    {
      "type": "any",
      "address": "0xa774E0BbB5dFB3973A083a756Cbf28429D1DFe42",
      "tokens": ["0xda4Dd9586D27202A338843Dd6B9824d267006783"]
    },
    {
      "type": "any",
      "address": "0xa8752333f6a6fe47323a4eDAC3D09Bb1048A0E23",
      "tokens": ["0x850aAB69f0e0171A9a49dB8BE3E71351c8247Df4"]
    },
    {
      "type": "any",
      "address": "0xA87bDdA360932cF11AeCf1369e8f08889326814e",
      "tokens": ["0xB2c1d397eC86Acb569CDab7889E66C3964fe43b6"]
    },
    {
      "type": "any",
      "address": "0xA97588986830962f01e1778B752775d40322827f",
      "tokens": ["0x429881672B9AE42b8EbA0E26cD9C73711b891Ca5"]
    },
    {
      "type": "any",
      "address": "0xaa3F69D6113f5BE55ec65e0B3ea48f834E41E16D",
      "tokens": ["0x1C7ede23b1361acC098A1e357C9085D131b34a01"]
    },
    {
      "type": "any",
      "address": "0xaBDA031246BD1De3D7b683455506D3d74a0E1a5B",
      "tokens": ["0x476c5E26a75bd202a9683ffD34359C0CC15be0fF"]
    },
    {
      "type": "any",
      "address": "0xac5F7B3220f8cc21AbbfCa952e30193a27DB3A3A",
      "tokens": ["0xEF53462838000184F35f7D991452e5f25110b207"]
    },
    {
      "type": "any",
      "address": "0xAFAace7138ab3c2BCb2DB4264F8312e1Bbb80653",
      "tokens": ["0x1A3496C18d558bd9C6C8f609E1B129f67AB08163"]
    },
    {
      "type": "any",
      "address": "0xaFb2780CBb58b2AF27023Eb2a0e60c8Ca0eEE9bb",
      "tokens": ["0xB8647e90C0645152Fccf4d9AbB6B59Eb4AA99052"]
    },
    {
      "type": "any",
      "address": "0xB01371072fDcB9B4433b855e16A682B461F94AB3",
      "tokens": ["0x4E15361FD6b4BB609Fa63C81A2be19d873717870"]
    },
    {
      "type": "any",
      "address": "0xb0FdcdD7E920A036331Abe9FFC7313322C0abba0",
      "tokens": ["0x97a9bac06f90940bCe9CAeC2b880ff17707519e4"]
    },
    {
      "type": "any",
      "address": "0xB1d6bc439F5D3bFbD828Da3D0848b0F3658c9Dc6",
      "tokens": ["0xa1faa113cbE53436Df28FF0aEe54275c13B40975"]
    },
    {
      "type": "any",
      "address": "0xb2004d3299eaad78951ba8502cC1840655061483",
      "tokens": ["0x33840024177A7DacA3468912363BeD8b425015c5"]
    },
    {
      "type": "any",
      "address": "0xB25e20De2F2eBb4CfFD4D16a55C7B395e8a94762",
      "tokens": ["0x01824357D7D7EAF4677Bc17786aBd26CBdEc9Ad7"]
    },
    {
      "type": "any",
      "address": "0xB53Ec4aCe420a62Cfb75aFdEba600D284777cd65",
      "tokens": ["0x57B946008913B82E4dF85f501cbAeD910e58D26C"]
    },
    {
      "type": "any",
      "address": "0xB72842D6F5feDf91D22d56202802Bb9A79C6322E",
      "tokens": ["0xdB25f211AB05b1c97D595516F45794528a807ad8"]
    },
    {
      "type": "any",
      "address": "0xb775fEeE081bd18CF0244fAE8ac641f1Bf7704b0",
      "tokens": ["0x66F73D0fD4161cfad4302DC145Ff994375c13475"]
    },
    {
      "type": "any",
      "address": "0xB808D767DDf0F61Ca62331c1bBbebe0530b41079",
      "tokens": ["0xE8521b61f64Fc45A0bC3db36D2A524fe61a69b52"]
    },
    {
      "type": "any",
      "address": "0xb8930BD2dD53D449f83466705827F3dBF90eA7Fc",
      "tokens": ["0xaa61D5dec73971CD4a026ef2820bB87b4a4Ed8d6"]
    },
    {
      "type": "any",
      "address": "0xb8a239996690430436425e249dC569D13D4C7AAD",
      "tokens": ["0x56de8BC61346321D4F2211e3aC3c0A7F00dB9b76"]
    },
    {
      "type": "any",
      "address": "0xbA40c1589B8120D995e56427CF2Ca63bF6A38e7E",
      "tokens": ["0xD528cf2E081f72908e086F8800977df826B5a483"]
    },
    {
      "type": "any",
      "address": "0xBaa75208D0ec8DDe89C036dD71E897C8df903f11",
      "tokens": ["0x3708DEA52A5846FD16d0060AaB01c87bb5932b02"]
    },
    {
      "type": "any",
      "address": "0xBAf8E9CA8693036BBD1e5B81b82F2359739eE5A6",
      "tokens": ["0xB4F74994FCBd60E1bC3603b9a33069eA1b32d4A4"]
    },
    {
      "type": "any",
      "address": "0xbB29D2A58d880Af8AA5859e30470134dEAf84F2B",
      "tokens": ["0x573d2505a7ee69D136A8667b4Cd915f039AC54e5"]
    },
    {
      "type": "any",
      "address": "0xbB3D3EE59002B7b9A0a276C269D60fbAc3EA65F8",
      "tokens": ["0x7aE0d42f23C33338dE15bFa89C7405c068d9dC0a"]
    },
    {
      "type": "any",
      "address": "0xBBB63f49Fe75CD82513c4a3da2eC80dD36A8448F",
      "tokens": ["0x3ebb4A4e91Ad83BE51F8d596533818b246F4bEe1"]
    },
    {
      "type": "any",
      "address": "0xbbc4A8d076F4B1888fec42581B6fc58d242CF2D5",
      "tokens": ["0x99D8a9C45b2ecA8864373A26D1459e3Dff1e17F3"]
    },
    {
      "type": "any",
      "address": "0xBBfE0B60dE96a189BF09079DE86A2Db7bF0C7883",
      "tokens": ["0x3C4008eca800Ec1283E4cf500E68D06BFaBc00a8"]
    },
    {
      "type": "basic",
      "address": "0xbd40733A2F223fF32195a759a81df25E35DD4dEA",
      "tokens": [
        "0x0F5D2fB29fb7d3CFeE444a200298f468908cC942",
        "0x1f9840a85d5aF5bf1D1762F925BDADdC4201F984",
        "0x2260FAC5E5542a773Aa44fBCfeDf7C193bc2C599",
        "0x2F109021aFe75B949429fe30523Ee7C0D5B27207",
        "0x3845badAde8e6dFF049820680d1F14bD3903a5d0",
        "0x6B175474E89094C44Da98b954EedeAC495271d0F",
        "0x7Fc66500c84A76Ad7e9c93437bFc5Ac33E2DDaE9",
        "0xA0b86991c6218b36c1d19D4a2e9Eb0cE3606eB48",
        "0xBB0E17EF65F82Ab018d8EDd776e8DD940327B28b",
        "0xC011a73ee8576Fb46F5E1c5751cA3B9Fe0af2a6F",
        "0xE74dC43867E0cbEB208F1a012fc60DcBbF0E3044",
        "0xd55236D48606c295adEbF129dAD04Fc74BFaA708",
        "0xdAC17F958D2ee523a2206206994597C13D831ec7",
        "ETH"
      ]
    },
    {
      "type": "any",
      "address": "0xbD83010eB60F12112908774998F65761cf9f6f9a",
      "tokens": ["0x62Dc4817588d53a056cBbD18231d91ffCcd34b2A"]
    },
    {
      "type": "any",
      "address": "0xBDba76fA2659c33ffCc2B0bc134c3A2c8a3Aa94d",
      "tokens": ["0x40986a85B4cFCDb054A6CBFB1210194fee51af88"]
    },
    {
      "type": "basic",
      "address": "0xBe008e52c5682A49dd0260735a26Aa221f303456",
      "tokens": ["0xdAC17F958D2ee523a2206206994597C13D831ec7"]
    },
    {
      "type": "any",
      "address": "0xc0330289B5509269bC312C83E5dB42Aeb259B687",
      "tokens": ["0x8dB253a1943DdDf1AF9bcF8706ac9A0Ce939d922"]
    },
    {
      "type": "any",
      "address": "0xC167f62e93775ACADeb3d2B0940bce560171Fdf3",
      "tokens": ["0x4d224452801ACEd8B2F0aebE155379bb5D594381"]
    },
    {
      "type": "any",
      "address": "0xc261b646f2e4B63068470666DB5Cc39E4BE743a8",
      "tokens": ["0x5F2080542ab6ae7e0b06778F0B2d263006297840"]
    },
    {
      "type": "any",
      "address": "0xc49F8B8a273456171A7e059ee90437EB51159Ec0",
      "tokens": ["0x40932D9cd67e89749406F16eDD2D211B7ab1ff50"]
    },
    {
      "type": "basic",
      "address": "0xC564EE9f21Ed8A2d8E7e76c085740d5e4c5FaFbE",
      "tokens": [
        "0x0000000000085d4780B73119b644AE5ecd22b376",
        "0x035dF12E0F3ac6671126525f1015E47D79dFEDDF",
        "0x03ab458634910AaD20eF5f1C8ee96F1D6ac54919",
        "0x054D64b73d3D8A21Af3D764eFd76bCaA774f3Bb2",
        "0x056Fd409E1d7A124BD7017459dFEa2F387b6d5Cd",
        "0x06a87F6aFEc4a739c367bEF69eEfE383D27106bd",
        "0x09617F6fD6cF8A71278ec86e23bBab29C04353a7",
        "0x09970aec766b6f3223aCA9111555E99DC50Ff13a",
        "0x0AeE8703D34DD9aE107386d3eFF22AE75Dd616D1",
        "0x0E29e5AbbB5FD88e28b2d355774e73BD47dE3bcd",
        "0x0bc529c00C6401aEF6D220BE8C6Ea1667F6Ad93e",
        "0x0c7D5ae016f806603CB1782bEa29AC69471CAb9c",
        "0x1117aC6Ad6Cdf1A3BC543baD3B133724620522d5",
        "0x12D102F06da35cC0111EB58017fd2Cd28537d0e1",
        "0x16ECCfDbb4eE1A85A33f3A9B21175Cd7Ae753dB4",
        "0x16ba8Efe847EBDFef99d399902ec29397D403C30",
        "0x177BA0cac51bFC7eA24BAd39d81dcEFd59d74fAa",
        "0x19D97D8fA813EE2f51aD4B4e04EA08bAf4DFfC28",
        "0x1A3496C18d558bd9C6C8f609E1B129f67AB08163",
        "0x1b40183EFB4Dd766f11bDa7A7c3AD8982e998421",
        "0x1cEB5cB57C4D4E2b2433641b95Dd330A33185A44",
        "0x2260FAC5E5542a773Aa44fBCfeDf7C193bc2C599",
        "0x226f7b842E0F0120b7E194D05432b3fd14773a9D",
        "0x22B6C31c2bEB8f2d0d5373146Eed41Ab9eDe3caf",
        "0x232FB065D9d24c34708eeDbF03724f2e95ABE768",
        "0x2370f9d504c7a6E775bf6E14B3F12846b594cD53",
        "0x2791BfD60D232150Bff86b39B7146c0eaAA2BA81",
        "0x2AF5D2aD76741191D15Dfe7bF6aC92d4Bd912Ca3",
        "0x2C9023bBc572ff8dc1228c7858A280046Ea8C9E5",
        "0x2ba592F78dB6436527729929AAf6c908497cB200",
        "0x31429d1856aD1377A8A0079410B297e1a9e214c2",
        "0x3432B6A60D23Ca0dFCa7761B7ab56459D9C964D0",
        "0x3472A5A71965499acd81997a54BBA8D852C6E53d",
        "0x36E43065e977bC72CB86Dbd8405fae7057CDC7fD",
        "0x3Dc7B06dD0B1f08ef9AcBbD2564f8605b4868EEA",
        "0x3aFfCCa64c2A6f4e3B6Bd9c64CD2C969EFd1ECBe",
        "0x3fa400483487A489EC9b1dB29C4129063EEC4654",
        "0x41D5D79431A913C4aE7d69a668ecdfE5fF9DFB68",
        "0x4688a8b1F292FDaB17E9a90c8Bc379dC1DBd8713",
        "0x4691937a7508860F876c9c0a2a617E7d9E945D4B",
        "0x46e9fE43470fafd690100C86037f9E566E24D480",
        "0x4C25Bdf026Ea05F32713F00f73Ca55857Fbf6342",
        "0x4D2eE5DAe46C86DA2FF521F7657dad98834f97b8",
        "0x514910771AF9Ca656af840dff83E8264EcF986CA",
        "0x5150956E082C748Ca837a5dFa0a7C10CA4697f9c",
        "0x57Ab1ec28D129707052df4dF418D58a2D46d5f51",
        "0x584bC13c7D411c00c01A62e8019472dE68768430",
        "0x6149C26Cd2f7b5CCdb32029aF817123F6E37Df5B",
        "0x6243d8CEA23066d098a15582d81a598b4e8391F4",
        "0x63b4f3e3fa4e438698CE330e365E831F7cCD1eF4",
        "0x672EF7E4Fe230B5cA1466C5fDD40588d30FdF90a",
        "0x68037790A0229e9Ce6EaA8A99ea92964106C4703",
        "0x6B175474E89094C44Da98b954EedeAC495271d0F",
        "0x6B3595068778DD592e39A122f4f5a5cF09C90fE2",
        "0x6B4c7A5e3f0B99FCD83e9c089BDDD6c7FCe5c611",
        "0x6c972b70c533E2E045F333Ee28b9fFb8D717bE69",
        "0x6e9730EcFfBed43fD876A264C982e254ef05a0DE",
        "0x7240aC91f01233BaAf8b064248E80feaA5912BA3",
        "0x74B988156925937bD4E082f0eD7429Da8eAea8Db",
        "0x7778360F035C589fCE2f4eA5786CbD8B36e5396B",
        "0x7815bDa662050D84718B988735218CFfd32f75ea",
        "0x7Fc66500c84A76Ad7e9c93437bFc5Ac33E2DDaE9",
        "0x7f3141c4D6b047fb930991b450f1eD996a51CB26",
        "0x853d955aCEf822Db058eb8505911ED77F175b99e",
        "0x865377367054516e17014CcdED1e7d814EDC9ce4",
        "0x8751D4196027d4e6DA63716fA7786B5174F04C15",
        "0x8888801aF4d980682e47f1A9036e589479e835C5",
        "0x90B831fa3Bebf58E9744A14D638E25B4eE06f9Bc",
        "0x92E187a03B6CD19CB6AF293ba17F2745Fd2357D5",
        "0x95aD61b0a150d79219dCF64E1E6Cc01f0B64C4cE",
        "0x95b3497bBcCcc46a8F45F5Cf54b0878b39f8D96C",
        "0x9695e0114e12C0d3A3636fAb5A18e6b737529023",
        "0xA0b86991c6218b36c1d19D4a2e9Eb0cE3606eB48",
        "0xA2b4C0Af19cC16a6CfAcCe81F192B024d625817D",
        "0xA36FDBBAE3c9d55a1d67EE5821d53B50B63A1aB9",
        "0xA5Ef74068d04ba0809B7379dD76Af5Ce34Ab7C57",
        "0xA8e7AD77C60eE6f30BaC54E2E7c0617Bd7B5A03E",
        "0xB62132e35a6c13ee1EE0f84dC5d40bad8d815206",
        "0xBA11D00c5f74255f56a5E366F4F77f5A186d7f55",
        "0xC011a73ee8576Fb46F5E1c5751cA3B9Fe0af2a6F",
        "0xC02aaA39b223FE8D0A0e5C4F27eAD9083C756Cc2",
        "0xD0660cD418a64a1d44E9214ad8e459324D8157f1",
        "0xD0Cd466b34A24fcB2f87676278AF2005Ca8A78c4",
        "0xD291E7a03283640FDc51b121aC401383A46cC623",
        "0xD49374D1D6d2b2D793035A0116F2b0D19230DE26",
        "0xD533a949740bb3306d119CC777fa900bA034cd52",
        "0xE0aD1806Fd3E7edF6FF52Fdb822432e847411033",
        "0xE4f726Adc8e89C6a6017F01eadA77865dB22dA14",
        "0xEA1ea0972fa092dd463f2968F9bB51Cc4c981D71",
        "0xEfc1C73A3D8728Dc4Cf2A18ac5705FE93E5914AC",
        "0xa02120696c7B8fE16C09C749E4598819b2B0E915",
        "0xa283aA7CfBB27EF0cfBcb2493dD9F4330E0fd304",
        "0xa7DE087329BFcda5639247F96140f9DAbe3DeED1",
        "0xaa61D5dec73971CD4a026ef2820bB87b4a4Ed8d6",
        "0xaaAEBE6Fe48E54f431b0C390CfaF0b017d09D42d",
        "0xb753428af26E81097e7fD17f40c88aaA3E04902c",
        "0xba100000625a3754423978a60c9317c58a424e3D",
        "0xdAC17F958D2ee523a2206206994597C13D831ec7",
        "0xdacD69347dE42baBfAEcD09dC88958378780FB62",
        "0xe1406825186D63980fd6e2eC61888f7B91C4bAe4",
        "0xe63d6B308BCe0F6193AeC6b7E6eBa005f41e36AB",
        "0xeDEec5691f23E4914cF0183A4196bBEb30d027a0",
        "0xf16e81dce15B08F326220742020379B855B87DF9",
        "0xf1F508c7C9f0d1b15a76fbA564eEf2d956220cf7"
      ]
    },
    {
      "type": "any",
      "address": "0xc5C71CD0b734Dae8c6eBa9D79C3Db693d112DDA1",
      "tokens": ["0xd98F75b1A3261dab9eEd4956c93F33749027a964"]
    },
    {
      "type": "any",
      "address": "0xc5e509bC8438d4F4ee355282eeb4af92AE14E43a",
      "tokens": ["0x9fa69536d1cda4A04cFB50688294de75B505a9aE"]
    },
    {
      "type": "any",
      "address": "0xc8a45dd787a301C38aD33f692f0d41C18590Ef94",
      "tokens": ["0x10010078a54396F62c96dF8532dc2B4847d47ED3"]
    },
    {
      "type": "any",
      "address": "0xc8f884783Ea40116ac7ee1893858C21d9d438b6c",
      "tokens": ["0xf460d98a3517b45Edd8063dd3847de92a8038aa2"]
    },
    {
      "type": "any",
      "address": "0xcaF5191fc480F43e4DF80106c7695ECA56E48B18",
      "tokens": ["0x7825e833D495F3d1c28872415a4aee339D26AC88"]
    },
    {
      "type": "any",
      "address": "0xcb56e96615bB22BF4d78390Ac79f4b5e9F582ccf",
      "tokens": ["0xb2ea51BAa12C461327d12A2069d47b30e680b69D"]
    },
    {
      "type": "any",
      "address": "0xcb69f7Ac645F5e09310b91445277A53F7fcb78cF",
      "tokens": ["0x2f4eb47A1b1F4488C71fc10e39a4aa56AF33Dd49"]
    },
    {
      "type": "any",
      "address": "0xcb9d0b8CfD8371143ba5A794c7218D4766c493e2",
      "tokens": ["0xba100000625a3754423978a60c9317c58a424e3D"]
    },
    {
      "type": "any",
      "address": "0xCC081220542a60A8Ea7963C4F53D522b503272c1",
      "tokens": ["0x22B48E1f20043D1Db5F2a11CbF1d520A4F20b198"]
    },
    {
      "type": "basic",
      "address": "0xCDd83050f045ab31B884f0Dc49581BC7b3e0B84C",
      "tokens": [
        "0x2260FAC5E5542a773Aa44fBCfeDf7C193bc2C599",
        "0x6B175474E89094C44Da98b954EedeAC495271d0F",
        "0xA0b86991c6218b36c1d19D4a2e9Eb0cE3606eB48",
        "0xdAC17F958D2ee523a2206206994597C13D831ec7",
        "ETH"
      ]
    },
    {
      "type": "any",
      "address": "0xCE3b8897BE065315C8eAB816A31153025ae428bE",
      "tokens": ["0xcf0C122c6b73ff809C693DB761e7BaeBe62b6a2E"]
    },
    {
      "type": "any",
      "address": "0xcea59DCE6A6d73a24e6d6944CFaBc330814c098A",
      "tokens": ["0x446F2A8A39Cc730ef378Be759A3c57f1a3fE824c"]
    },
    {
      "type": "any",
      "address": "0xcf799767d366d789e8B446981C2D578E241fa25c",
      "tokens": ["0x0C10bF8FcB7Bf5412187A595ab97a3609160b5c6"]
    },
    {
      "type": "any",
      "address": "0xCfa8F0Aed0414A98f99f1Ea29ddF23f6E1370c13",
      "tokens": ["0x4e3FBD56CD56c3e72c1403e103b45Db9da5B9D2B"]
    },
    {
      "type": "any",
      "address": "0xcFD5868fbF612bd8907827f012d71f3C7BA6C943",
      "tokens": ["0x2260FAC5E5542a773Aa44fBCfeDf7C193bc2C599"]
    },
    {
      "type": "basic",
      "address": "0xd0a4297F433a642912583b2b644801a6e250031e",
      "tokens": ["0x95b3497bBcCcc46a8F45F5Cf54b0878b39f8D96C"]
    },
    {
      "type": "any",
      "address": "0xD10e226F85DFb53Aa2f9F3D297e521E1eE4F1Bf7",
      "tokens": ["0x47BE779De87de6580d0548cde80710a93c502405"]
    },
    {
      "type": "any",
      "address": "0xd13eB71515DC48a8a367D12F844e5737bab415dF",
      "tokens": ["0x4Fabb145d64652a948d72533023f6E7A623C7C53"]
    },
    {
      "type": "any",
      "address": "0xd145261DD80BC5388ea8f437D503897060410f1C",
      "tokens": ["0x8A9C67fee641579dEbA04928c4BC45F66e26343A"]
    },
    {
      "type": "any",
      "address": "0xD17652350Cfd2A37bA2f947C910987a3B1A1c60d",
      "tokens": ["0x67C5870b4A41D4Ebef24d2456547A03F1f3e094B"]
    },
    {
      "type": "any",
      "address": "0xd1a891E6eCcB7471Ebd6Bc352F57150d4365dB21",
      "tokens": ["0x4e352cF164E64ADCBad318C3a1e222E9EBa4Ce42"]
    },
    {
      "type": "any",
      "address": "0xD22e210785902c39B579565e931517E5Bd34A69a",
      "tokens": ["0x7D1AfA7B718fb893dB30A3aBc0Cfc608AaCfeBB0"]
    },
    {
      "type": "any",
      "address": "0xD2aF5442bd47461B37726fD323D95E569973fe6d",
      "tokens": ["0x65Def5029A0e7591e46B38742bFEdd1Fb7b24436"]
    },
    {
      "type": "any",
      "address": "0xD2c244D5c3b530b9310C34962bF9B48c08dC0BcB",
      "tokens": ["0xF6134E74b7a4ee23A888436E53e77F83e62E8df8"]
    },
    {
      "type": "any",
      "address": "0xd4143E8dB48a8f73afCDF13D7B3305F28DA38116",
      "tokens": ["0x5f6c5C2fB289dB2228d159C69621215e354218d7"]
    },
    {
      "type": "any",
      "address": "0xD5eBD23D5eb968c2efbA2B03F27Ee61718609A71",
      "tokens": ["0x7777777777697cFEECF846A76326dA79CC606517"]
    },
    {
      "type": "any",
      "address": "0xD6040966181C9D1B28158335780dC42514B119e7",
      "tokens": ["0x92CfbEC26C206C90aeE3b7C66A9AE673754FaB7e"]
    },
    {
      "type": "any",
      "address": "0xD6Cce248263ea1e2b8cB765178C944Fc16Ed0727",
      "tokens": ["0x721A1B990699eE9D90b6327FaaD0A3E840aE8335"]
    },
    {
      "type": "any",
      "address": "0xd76B758a552f763cD496F1fB06A8F56364122675",
      "tokens": ["0x29b3d220f0f1E37b342Cf7c48c1164BF5bf79eFa"]
    },
    {
      "type": "basic",
      "address": "0xD779967F8B511C5edf39115341B310022900eFED",
      "tokens": [
        "0x02F2D4a04E6E01aCE88bD2Cd632875543b2eF577",
        "0x0fF6ffcFDa92c53F615a4A75D982f399C989366b",
        "0xBc17729fDf562723f0267F79FF25aDE441056d87",
        "0xE4CFE9eAa8Cdb0942A80B7bC68fD8Ab0F6D44903",
        "0xFD9cd8c0D18cD7e06958F3055e0Ec3ADbdba0B17",
        "0xc17fbe1d709dDf6C0B6665Dd0591046815AC7554",
        "0xd714d91A169127e11D8FAb3665d72E8b7ef9Dbe2",
        "0xdAC17F958D2ee523a2206206994597C13D831ec7",
        "ETH"
      ]
    },
    {
      "type": "any",
      "address": "0xD8E473bb0A7090C6a58A0E5ff2D0159b671DC4aB",
      "tokens": ["0xe7aE6D0C56CACaf007b7e4d312f9af686a9E9a04"]
    },
    {
      "type": "any",
      "address": "0xD91903D548f19C0FC0a6B9ED09D2F72b4dFe7144",
      "tokens": ["0xd5b87813A5ecb2eaC24b6B3F2d4b8b69F583aF4e"]
    },
    {
      "type": "any",
      "address": "0xd9A807E9d2F61B0098B4c3f79b2Dfb9Bc2E181ae",
      "tokens": ["0xaDB2437e6F65682B85F814fBc12FeC0508A7B1D0"]
    },
    {
      "type": "any",
      "address": "0xdB12c7E30Dc2A2C421724D07C7A09147bD9f61bb",
      "tokens": ["0xE1c7E30C42C24582888C758984f6e382096786bd"]
    },
    {
      "type": "any",
      "address": "0xDd98B79b36c77Ee1F23f37B61e58A61cc3D5aceF",
      "tokens": ["0x0f51bb10119727a7e5eA3538074fb341F56B09Ad"]
    },
    {
      "type": "any",
      "address": "0xdE22E15C6c21B6A8a1266B171FF7F3905C4B1109",
      "tokens": ["0x947AEb02304391f8fbE5B25D7D98D649b57b1788"]
    },
    {
      "type": "any",
      "address": "0xdE58658a05a8cE87BB8Ab96a05A4C4544938E28F",
      "tokens": ["0x993864E43Caa7F7F12953AD6fEb1d1Ca635B875F"]
    },
    {
      "type": "any",
      "address": "0xdFb5A6b5136186f4fFcf3FE055B48F27793CdBD2",
      "tokens": ["0x332E824e46FcEeB9E59ba9491B80d3e6d42B0B59"]
    },
    {
      "type": "any",
      "address": "0xDfed31E640b7280F76f046a97179E5E369D209b5",
      "tokens": ["0xAEcc217a749c2405b5ebC9857a16d58Bdc1c367F"]
    },
    {
      "type": "any",
      "address": "0xe008ff5483D5C0214911ba6CBDACcf822436D165",
      "tokens": ["0xDFDb7f72c1F195C5951a234e8DB9806EB0635346"]
    },
    {
      "type": "any",
      "address": "0xE238Ce130E8d0Bed5FaB0bb52Fed6396F1aAa192",
      "tokens": ["0x90B831fa3Bebf58E9744A14D638E25B4eE06f9Bc"]
    },
    {
      "type": "any",
      "address": "0xe2D27f06F63d98b8e11b38b5b08A75D0c8dD62B9",
      "tokens": ["0xa283aA7CfBB27EF0cfBcb2493dD9F4330E0fd304"]
    },
    {
      "type": "any",
      "address": "0xe2f28d24A2c6a69de859DFdEFE347c9b25ad6aA2",
      "tokens": ["0x0100546F2cD4C9D97f798fFC9755E47865FF7Ee6"]
    },
    {
      "type": "any",
      "address": "0xE3AB61371ECc88534C522922a026f2296116C109",
      "tokens": ["0x054f76beED60AB6dBEb23502178C52d6C5dEbE40"]
    },
    {
      "type": "any",
      "address": "0xE408849D21646a42fD5E36CC520b26e7cDd62370",
      "tokens": ["0xe0cCa86B254005889aC3a81e737f56a14f4A38F5"]
    },
    {
      "type": "basic",
      "address": "0xE4cf417081A0Ab3f964b44D904BC2b534351A9a7",
      "tokens": [
        "0x2260FAC5E5542a773Aa44fBCfeDf7C193bc2C599",
        "0x6B175474E89094C44Da98b954EedeAC495271d0F",
        "0xA0b86991c6218b36c1d19D4a2e9Eb0cE3606eB48",
        "ETH"
      ]
    },
    {
      "type": "any",
      "address": "0xe5130D3DbfaC6Ae7d73a24D719762df74d8E4c27",
      "tokens": ["0x4057Db5bD9f67A566aA10E5587b1a964afFc6a16"]
    },
    {
      "type": "any",
      "address": "0xe5CF1558A1470cb5C166c2e8651eD0F3c5fb8F42",
      "tokens": ["0x491604c0FDF08347Dd1fa4Ee062a822A5DD06B5D"]
    },
    {
      "type": "any",
      "address": "0xE613a914bbb433855378183c3aB13003285da40A",
      "tokens": ["0x591127253E40d4f63bF29CcF3D81FD062A149C8c"]
    },
    {
      "type": "any",
      "address": "0xE6B9d092223f39013656702A40dbE6B7DeCc5746",
      "tokens": ["0x2260FAC5E5542a773Aa44fBCfeDf7C193bc2C599"]
    },
    {
      "type": "any",
      "address": "0xe6D9C0aCF30194E2a5ae9C1c8342aC49e98A4B0A",
      "tokens": ["0x970B9bB2C0444F5E81e9d0eFb84C8ccdcdcAf84d"]
    },
    {
      "type": "any",
      "address": "0xE705aF5f63fcaBDCDF5016aA838EAaac35D12890",
      "tokens": ["0x1a7e4e63778B4f12a199C062f3eFdD288afCBce8"]
    },
    {
      "type": "any",
      "address": "0xe7619904607FD71e3D95BB6cf2971dB4aD6027B5",
      "tokens": ["0x37129b96896891e56bc099540fe7D1841005A367"]
    },
    {
      "type": "any",
      "address": "0xe7F04E0FBdE4b16FEb4a67747133F251E4DBcCd7",
      "tokens": ["0x15b7c0c907e4C6b9AdaAaabC300C08991D6CEA05"]
    },
    {
      "type": "any",
      "address": "0xE84CEA9df2D6a6010C0Bd74b803F6372534e75e9",
      "tokens": ["0xa350DA05405cc204e551C4eeD19C3039646528d5"]
    },
    {
      "type": "any",
      "address": "0xE87d84DcBb848fe94C6dAEdc9c81C913F707F2D2",
      "tokens": ["0x3f5294DF68F871241c4B18fcF78ebD8Ac18aB654"]
    },
    {
      "type": "any",
      "address": "0xeA3cCA5347D1169Cf87E2E4358612E75cD7dE480",
      "tokens": ["0x85F17Cf997934a597031b2E18a9aB6ebD4B9f6a4"]
    },
    {
      "type": "any",
      "address": "0xeA928a8d09E11c66e074fBf2f6804E19821F438D",
      "tokens": ["0xA0b86991c6218b36c1d19D4a2e9Eb0cE3606eB48"]
    },
    {
      "type": "any",
      "address": "0xeBE58381406D2c9BC9F68f541D503bA4F1A29fDF",
      "tokens": ["0x15D4c048F83bd7e37d49eA4C83a07267Ec4203dA"]
    },
    {
      "type": "basic",
      "address": "0xEC4486a90371c9b66f499Ff3936F29f0D5AF8b7E",
      "tokens": [
        "0x2260FAC5E5542a773Aa44fBCfeDf7C193bc2C599",
        "0x6B175474E89094C44Da98b954EedeAC495271d0F",
        "0x6B3595068778DD592e39A122f4f5a5cF09C90fE2",
        "0x7Fc66500c84A76Ad7e9c93437bFc5Ac33E2DDaE9",
        "0xA0b86991c6218b36c1d19D4a2e9Eb0cE3606eB48",
        "0xD533a949740bb3306d119CC777fa900bA034cd52",
        "0xdAC17F958D2ee523a2206206994597C13D831ec7",
        "ETH"
      ]
    },
    {
      "type": "any",
      "address": "0xed28B1890fBB4aA9ded528c1034fED278ff68f5d",
      "tokens": ["0x16594930D16f3970e1a4317c6016555cb2e7b7Fc"]
    },
    {
      "type": "any",
      "address": "0xeD3516AA436B630b50960A3D19bA7a2e46D0E368",
      "tokens": ["0xAaE3Cf9968D26925BDb73cE3864e0084a20f4687"]
    },
    {
      "type": "any",
      "address": "0xEDE1B2f557942c9132c0eA1b7f20A63f711982D4",
      "tokens": ["0x8CC0F052fff7eaD7f2EdCCcaC895502E884a8a71"]
    },
    {
      "type": "any",
      "address": "0xee9762352f63f4387af40D58291612067727457D",
      "tokens": ["0xdAC17F958D2ee523a2206206994597C13D831ec7"]
    },
    {
      "type": "any",
      "address": "0xef5cE7411B389e004A73B37ACfC51A8218322a6c",
      "tokens": ["0x4f640F2529ee0cF119A2881485845FA8e61A782A"]
    },
    {
      "type": "any",
      "address": "0xeFAeeE334F0Fd1712f9a8cc375f427D9Cdd40d73",
      "tokens": ["0x067edE5097574b387ff30999e3a1775f3D7D569d"]
    },
    {
      "type": "any",
      "address": "0xefbE7ba6382733473C999088f2020B75c4678c76",
      "tokens": ["0xB1f66997A5760428D3a87D68b90BfE0aE64121cC"]
    },
    {
      "type": "any",
      "address": "0xf1b7980826Cd89A99e45eb4236492FD42d463660",
      "tokens": ["0xD9016A907Dc0ECfA3ca425ab20B6b785B42F2373"]
    },
    {
      "type": "any",
      "address": "0xf1c55367b8E4742a7abF80968705795b07536804",
      "tokens": ["0xebF2096E01455108bAdCbAF86cE30b6e5A72aa52"]
    },
    {
      "type": "basic",
      "address": "0xF2c78A59885f1E5548E1FcD2A900EF6cF8c279d4",
      "tokens": [
        "0x226f7b842E0F0120b7E194D05432b3fd14773a9D",
        "0x31429d1856aD1377A8A0079410B297e1a9e214c2",
        "0x3Dc7B06dD0B1f08ef9AcBbD2564f8605b4868EEA",
        "0xA5Ef74068d04ba0809B7379dD76Af5Ce34Ab7C57",
        "0xB4A3B0Faf0Ab53df58001804DdA5Bfc6a3D59008"
      ]
    },
    {
      "type": "any",
      "address": "0xF331b2C406fEF2539e9b1150345575feb9f0323c",
      "tokens": ["0x73B708E84837FFCcDE2933e3A1531fe61D5e80Ef"]
    },
    {
      "type": "any",
      "address": "0xF49818b5d7dE5B0DBfcCb3Ddcd14e1f0AA1A6f01",
      "tokens": ["0xBC6DA0FE9aD5f3b0d58160288917AA56653660E9"]
    },
    {
      "type": "any",
      "address": "0xF545cd9Ec67770748c3C2bDB4b7511A86f00aF0A",
      "tokens": ["0x9528cCEb678B90dAf02cA5cA45622D5cBaF58A30"]
    },
    {
      "type": "basic",
      "address": "0xF62385C78f3BDBff33145703546b0377853AAa77",
      "tokens": [
        "0x2260FAC5E5542a773Aa44fBCfeDf7C193bc2C599",
        "0x6B175474E89094C44Da98b954EedeAC495271d0F",
        "0xA0b86991c6218b36c1d19D4a2e9Eb0cE3606eB48",
        "0xdAC17F958D2ee523a2206206994597C13D831ec7",
        "ETH"
      ]
    },
    {
      "type": "any",
      "address": "0xF7428FFCb2581A2804998eFbB036A43255c8A8D3",
      "tokens": ["0xF6650117017FFD48B725B4EC5A00B414097108A7"]
    },
    {
      "type": "any",
      "address": "0xf751575ED3390f6C02B4358f9E165e7B44877032",
      "tokens": ["0x0000000000085d4780B73119b644AE5ecd22b376"]
    },
    {
      "type": "any",
      "address": "0xF75565B89BA076b8fc7B9708d14855FD3dA89e97",
      "tokens": ["0x4374F26F0148a6331905eDf4cD33B89d8Eed78d1"]
    },
    {
      "type": "any",
      "address": "0xF7fbaa0328C5FaeE1a0B2155065804F4077284e1",
      "tokens": ["0xAFCdd4f666c84Fed1d8BD825aA762e3714F652c9"]
    },
    {
      "type": "any",
      "address": "0xF887906E130349A624ffA3CF1FA5b56f48b11c08",
      "tokens": ["0x16B3E050e9e2f0Ac4f1BEA1b3E4fdc43d7f062Dd"]
    },
    {
      "type": "any",
      "address": "0xf8a363Cf116b6B633faEDF66848ED52895CE703b",
      "tokens": ["0x8A7aDc1B690E81c758F1BD0F72DFe27Ae6eC56A5"]
    },
    {
      "type": "any",
      "address": "0xF9cFbDd3120F59f261f0dB3610d683Fe0337eB20",
      "tokens": ["0x6b37374FE7980Ae33FC87B0d66A490Ec6903e87a"]
    },
    {
      "type": "any",
      "address": "0xfA9343C3897324496A05fC75abeD6bAC29f8A40f",
      "tokens": ["0x000000000000d0151E748d25b766e77efe2A6c83"]
    },
    {
      "type": "any",
      "address": "0xFaFA220145DfA5C3Ec85B6FA8a75aEE2451CDe5E",
      "tokens": ["0x4Fabb145d64652a948d72533023f6E7A623C7C53"]
    },
    {
      "type": "any",
      "address": "0xFC2AFD7EbF2E0ca69340Cd9f466177E23812CF5a",
      "tokens": ["0xEA1ea0972fa092dd463f2968F9bB51Cc4c981D71"]
    },
    {
      "type": "any",
      "address": "0xfc5C0e5d0BA6386fbb7d921E5073FD04082a5b49",
      "tokens": ["0x13C2fab6354d3790D8ece4f0f1a3280b4A25aD96"]
    },
    {
      "type": "basic",
      "address": "0xFc7cc7C7e7985316d23104B9689C511134f59bc8",
      "tokens": [
        "0x2260FAC5E5542a773Aa44fBCfeDf7C193bc2C599",
        "0xA0b86991c6218b36c1d19D4a2e9Eb0cE3606eB48",
        "0xbcD4b7dE6fde81025f74426D43165a5b0D790Fdd",
        "0xdAC17F958D2ee523a2206206994597C13D831ec7",
        "ETH"
      ]
    },
    {
      "type": "any",
      "address": "0xfCB7388EEf472293290B15027642702EBf57250A",
      "tokens": ["0xC19B6A4Ac7C7Cc24459F08984Bbd09664af17bD1"]
    },
    {
      "type": "any",
      "address": "0xFD33e5413E28142a14033cb0a4b0c7F98AE76da1",
      "tokens": ["0x81f8f0bb1cB2A06649E51913A151F0E7Ef6FA321"]
    },
    {
      "type": "any",
      "address": "0xFE77d71bAf7A6CdabbD63A2AD1e0aDb68ca64c06",
      "tokens": ["0x64A77277e37D44957FE5815d6FF442ab8b16cC29"]
    },
    {
      "type": "any",
      "address": "0xfEdADCE4361658AD34410F02De20aF217B0A9048",
      "tokens": ["0x45fDb1b92a649fb6A64Ef1511D3Ba5Bf60044838"]
    },
    {
      "type": "any",
      "address": "0xff33523a99340161e4E456166C22bE78d8675c07",
      "tokens": ["0x456125Cd98107ae0480Ba566f1b716D48Ba31453"]
    }
  ]
}
