{
  "projectId": "deri",
  "timestamp": 1769460088819,
  "escrows": [
    {
      "address": "arb1:0xD4FE46D2533E7d03382ac6cACF0547F336e59DC0",
      "name": "Bridge",
      "category": "rollup-secured",
      "bridgeType": "canonical",
      "nameCategory": "canonical-trust-minimized",
      "additionalTrust": false,
      "categoryReason": "Escrow controlled by Rollup Governance",
      "admin": "arb1:0x27C7Bfd2cC11429e9b80c443b42FDBe4754F6c91",
      "adminName": "Rollup Governance",
      "isRollupControlled": true,
      "tokens": [
        {
          "symbol": "ETH",
          "valueUsd": 16901.19,
          "amount": 5.77,
          "issuer": null,
          "source": "canonical"
        }
      ],
      "totalValueUsd": 16901.19,
      "source": "canonical",
      "description": "Escrow contract for the project's gas token (can be different from ETH). Keeps a list of allowed Inboxes and Outboxes for canonical bridge messaging."
    }
  ],
  "externalTokens": [],
  "summary": {
    "totalTvl": 16901.19,
    "nativeTvl": 0,
    "byNameCategory": {
      "canonicalTrustMinimized": 16901.19,
      "canonicalAdditionalTrust": 0,
      "external": 0
    },
    "externalBreakdown": {
      "issuerSecured": 0,
      "additionalTrust": 0
    },
    "canonicalTvl": 16901.19,
    "externalTvl": 0,
    "apiCanonicalTvl": 16901.19,
    "apiExternalTvl": 0
  },
  "externalTokensSummary": {
    "totalCount": 0,
    "totalValue": 0,
    "byProtocol": {},
    "byNameCategory": {}
  }
}